[
  {
    "name": "Area 51",
    "id": "sslg1",
    "details": "Sega Saturn light gun game",
    "igdbId": 39769,
    "gbId": 103,
    "gbGuid": "3030-103",
    "tgdbId": null,
    "category": "lightGun"
  },
  {
    "name": "Chaos Control",
    "id": "sslg2",
    "details": "Sega Saturn light gun game",
    "igdbId": 176140,
    "gbId": 17289,
    "gbGuid": "3030-17289",
    "tgdbId": null,
    "category": "lightGun"
  },
  {
    "name": "Corpse Killer",
    "id": "sslg3",
    "details": "Sega Saturn light gun game",
    "igdbId": 5372,
    "gbId": 2817,
    "gbGuid": "3030-2817",
    "tgdbId": null,
    "category": "lightGun"
  },
  {
    "name": "Crypt Killer",
    "id": "sslg4",
    "details": "Sega Saturn light gun game",
    "igdbId": 20737,
    "gbId": 550,
    "gbGuid": "3030-550",
    "tgdbId": null,
    "category": "lightGun"
  },
  {
    "name": "Death Crimson",
    "id": "sslg5",
    "details": "Sega Saturn light gun game",
    "igdbId": 54917,
    "gbId": 60543,
    "gbGuid": "3030-60543",
    "tgdbId": null,
    "category": "lightGun"
  },
  {
    "name": "Die Hard Trilogy",
    "id": "sslg6",
    "details": "Sega Saturn light gun game",
    "igdbId": 8234,
    "gbId": 19345,
    "gbGuid": "3030-19345",
    "tgdbId": null,
    "category": "lightGun"
  },
  {
    "name": "The House of the Dead",
    "id": "sslg7",
    "details": "Sega Saturn light gun game",
    "igdbId": 2469,
    "gbId": 508,
    "gbGuid": "3030-508",
    "tgdbId": null,
    "category": "lightGun"
  },
  {
    "name": "Mighty Hits",
    "id": "sslg8",
    "details": "Sega Saturn light gun game",
    "igdbId": 45487,
    "gbId": 33678,
    "gbGuid": "3030-33678",
    "tgdbId": null,
    "category": "lightGun"
  },
  {
    "name": "Maximum Force",
    "id": "sslg9",
    "details": "Sega Saturn light gun game",
    "igdbId": 36573,
    "gbId": 22180,
    "gbGuid": "3030-22180",
    "tgdbId": null,
    "category": "lightGun"
  },
  {
    "name": "Mechanical Violator Hakaider: Last Judgement",
    "id": "sslg10",
    "details": "Sega Saturn light gun game",
    "igdbId": 66147,
    "gbId": 33667,
    "gbGuid": "3030-33667",
    "tgdbId": null,
    "category": "lightGun"
  },
  {
    "name": "Policenauts",
    "id": "sslg11",
    "details": "Sega Saturn light gun game (contains light-gun sequences)",
    "igdbId": 4290,
    "gbId": 15090,
    "gbGuid": "3030-15090",
    "tgdbId": null,
    "category": "lightGun"
  },
  {
    "name": "Scud: The Disposable Assassin",
    "id": "sslg12",
    "details": "Sega Saturn light gun game",
    "igdbId": 45483,
    "gbId": 11835,
    "gbGuid": "3030-11835",
    "tgdbId": null,
    "category": "lightGun"
  },
  {
    "name": "Virtua Cop",
    "id": "sslg13",
    "details": "Sega Saturn light gun game",
    "igdbId": 6289,
    "gbId": 10543,
    "gbGuid": "3030-10543",
    "tgdbId": null,
    "category": "lightGun"
  },
  {
    "name": "Virtua Cop 2",
    "id": "sslg14",
    "details": "Sega Saturn light gun game",
    "igdbId": 2470,
    "gbId": 9341,
    "gbGuid": "3030-9341",
    "tgdbId": null,
    "category": "lightGun"
  }
]