[
  {
    "name": "Dragon Ball Z: Shin Saiya-jin Zetsumetsu Keikaku - Chikyuu-hen",
    "id": "bplt1",
    "details": "Bandai Playdia launch title",
    "igdbId": 66082,
    "gbId": 34486,
    "gbGuid": "3030-34486",
    "tgdbId": null,
    "category": "launchTitle"
  },
  {
    "name": "Bishoujo Senshi Sailor Moon S — Quiz Taiketsu! Sailor Power Kesshuu",
    "id": "bplt2",
    "details": "Bandai Playdia launch title",
    "igdbId": 138044,
    "gbId": 41295,
    "gbGuid": "3030-41295",
    "tgdbId": null,
    "category": "launchTitle"
  },
  {
    "name": "SD Gundam Daizukan",
    "id": "bplt3",
    "details": "Bandai Playdia launch title",
    "igdbId": 65997,
    "gbId": 35037,
    "gbGuid": "3030-35037",
    "tgdbId": null,
    "category": "launchTitle"
  }
]