[
  {
    "name": "A-Rank Thunder Tanjouhen",
    "details": [
      "Sega CD exclusive"
    ],
    "id": "scd0",
    "igdbId": 5355,
    "gbId": 46881,
    "gbGuid": "3030-46881",
    "tgdbId": 41470,
    "isExclusive": [
      {
        "name": "Sega CD",
        "id": "ccl15",
        "igdbId": 78,
        "gbId": 29,
        "gbGuid": "3045-29",
        "tgdbId": 21
      }
    ],
    "isLaunchTitle": false,
    "special": []
  },
  {
    "name": "A/X-101",
    "details": [
      "Sega CD exclusive"
    ],
    "id": "scd1",
    "igdbId": 5360,
    "gbId": 23240,
    "gbGuid": "3030-23240",
    "tgdbId": 4937,
    "isExclusive": [
      {
        "name": "Sega CD",
        "id": "ccl15",
        "igdbId": 78,
        "gbId": 29,
        "gbGuid": "3045-29",
        "tgdbId": 21
      }
    ],
    "isLaunchTitle": false,
    "special": []
  },
  {
    "name": "Android Assault: The Revenge of Bari-Arm",
    "details": [
      "Sega CD exclusive"
    ],
    "id": "scd2",
    "igdbId": 5358,
    "gbId": 23241,
    "gbGuid": "3030-23241",
    "tgdbId": 4936,
    "isExclusive": [
      {
        "name": "Sega CD",
        "id": "ccl15",
        "igdbId": 78,
        "gbId": 29,
        "gbGuid": "3045-29",
        "tgdbId": 21
      }
    ],
    "isLaunchTitle": false,
    "special": []
  },
  {
    "name": "Anett Futatabi",
    "details": [
      "Sega CD exclusive"
    ],
    "id": "scd3",
    "igdbId": null,
    "gbId": 9159,
    "gbGuid": "3030-9159",
    "tgdbId": 25432,
    "isExclusive": [
      {
        "name": "Sega CD",
        "id": "ccl15",
        "igdbId": 78,
        "gbId": 29,
        "gbGuid": "3045-29",
        "tgdbId": 21
      }
    ],
    "isLaunchTitle": false,
    "special": []
  },
  {
    "name": "BattleCorps",
    "details": [
      "Sega CD exclusive"
    ],
    "id": "scd4",
    "igdbId": 46423,
    "gbId": 210,
    "gbGuid": "3030-210",
    "tgdbId": 4940,
    "isExclusive": [
      {
        "name": "Sega CD",
        "id": "ccl15",
        "igdbId": 78,
        "gbId": 29,
        "gbGuid": "3045-29",
        "tgdbId": 21
      }
    ],
    "isLaunchTitle": false,
    "special": []
  },
  {
    "name": "BlackHole Assault",
    "id": "scd5",
    "details": [
      "Sega CD launch title"
    ],
    "igdbId": 5365,
    "gbId": 37977,
    "gbGuid": "3030-37977",
    "tgdbId": 19298,
    "isLaunchTitle": [
      {
        "name": "Sega CD",
        "id": "ccl15",
        "igdbId": 78,
        "gbId": 29,
        "gbGuid": "3045-29",
        "tgdbId": 21
      }
    ],
    "isExclusive": false,
    "special": []
  },
  {
    "name": "Bouncers",
    "details": [
      "Sega CD exclusive"
    ],
    "id": "scd6",
    "igdbId": 46422,
    "gbId": 7462,
    "gbGuid": "3030-7462",
    "tgdbId": 4943,
    "isExclusive": [
      {
        "name": "Sega CD",
        "id": "ccl15",
        "igdbId": 78,
        "gbId": 29,
        "gbGuid": "3045-29",
        "tgdbId": 21
      }
    ],
    "isLaunchTitle": false,
    "special": []
  },
  {
    "name": "Captain Tsubasa",
    "details": [
      "Sega CD exclusive"
    ],
    "id": "scd7",
    "igdbId": 5369,
    "gbId": 38265,
    "gbGuid": "3030-38265",
    "tgdbId": 23986,
    "isExclusive": [
      {
        "name": "Sega CD",
        "id": "ccl15",
        "igdbId": 78,
        "gbId": 29,
        "gbGuid": "3045-29",
        "tgdbId": 21
      }
    ],
    "isLaunchTitle": false,
    "special": []
  },
  {
    "name": "Chuck Rock",
    "id": "scd8",
    "details": [
      "Sega CD launch title"
    ],
    "igdbId": 4516,
    "gbId": 2941,
    "gbGuid": "3030-2941",
    "tgdbId": 1738,
    "isLaunchTitle": [
      {
        "name": "Sega CD",
        "id": "ccl15",
        "igdbId": 78,
        "gbId": 29,
        "gbGuid": "3045-29",
        "tgdbId": 21
      }
    ],
    "isExclusive": false,
    "special": []
  },
  {
    "name": "Cobra Command",
    "id": "scd9",
    "details": [
      "Sega CD launch title"
    ],
    "igdbId": 5371,
    "gbId": 30888,
    "gbGuid": "3030-30888",
    "tgdbId": 1676,
    "isLaunchTitle": [
      {
        "name": "Sega CD",
        "id": "ccl15",
        "igdbId": 78,
        "gbId": 29,
        "gbGuid": "3045-29",
        "tgdbId": 21
      }
    ],
    "isExclusive": false,
    "special": []
  },
  {
    "name": "Dark Wizard",
    "details": [
      "Sega CD exclusive"
    ],
    "id": "scd10",
    "igdbId": 5374,
    "gbId": 15251,
    "gbGuid": "3030-15251",
    "tgdbId": 4954,
    "isExclusive": [
      {
        "name": "Sega CD",
        "id": "ccl15",
        "igdbId": 78,
        "gbId": 29,
        "gbGuid": "3045-29",
        "tgdbId": 21
      }
    ],
    "isLaunchTitle": false,
    "special": []
  },
  {
    "name": "Dungeon Explorer",
    "id": "scd11",
    "details": [
      "Sega CD Team Player compatible title"
    ],
    "igdbId": 19742,
    "gbId": 28218,
    "gbGuid": "3030-28218",
    "special": [
      {
        "value": "Sega CD Team Player compatible title",
        "forPlatform": {
          "name": "Sega CD",
          "id": "ccl15",
          "igdbId": 78,
          "gbId": 29,
          "gbGuid": "3045-29",
          "tgdbId": 21
        }
      }
    ],
    "isExclusive": false,
    "isLaunchTitle": false
  },
  {
    "name": "Dynamic Country Club: 3D Golf Simulation",
    "id": "scd12",
    "details": [
      "Sega CD Team Player compatible title"
    ],
    "igdbId": 45873,
    "gbId": null,
    "gbGuid": null,
    "special": [
      {
        "value": "Sega CD Team Player compatible title",
        "forPlatform": {
          "name": "Sega CD",
          "id": "ccl15",
          "igdbId": 78,
          "gbId": 29,
          "gbGuid": "3045-29",
          "tgdbId": 21
        }
      }
    ],
    "isExclusive": false,
    "isLaunchTitle": false
  },
  {
    "name": "ESPN NBA HangTime '95",
    "details": [
      "Sega CD exclusive"
    ],
    "id": "scd13",
    "igdbId": 46406,
    "gbId": 10512,
    "gbGuid": "3030-10512",
    "tgdbId": 31785,
    "isExclusive": [
      {
        "name": "Sega CD",
        "id": "ccl15",
        "igdbId": 78,
        "gbId": 29,
        "gbGuid": "3045-29",
        "tgdbId": 21
      }
    ],
    "isLaunchTitle": false,
    "special": []
  },
  {
    "name": "ESPN NBA HangTime '95",
    "id": "scd14",
    "details": [
      "Sega CD Team Player compatible title"
    ],
    "igdbId": 46406,
    "gbId": null,
    "gbGuid": null,
    "special": [
      {
        "value": "Sega CD Team Player compatible title",
        "forPlatform": {
          "name": "Sega CD",
          "id": "ccl15",
          "igdbId": 78,
          "gbId": 29,
          "gbGuid": "3045-29",
          "tgdbId": 21
        }
      }
    ],
    "isExclusive": false,
    "isLaunchTitle": false
  },
  {
    "name": "ESPN National Hockey Night",
    "id": "scd15",
    "details": [
      "Sega CD Team Player compatible title"
    ],
    "igdbId": 5381,
    "gbId": 30852,
    "gbGuid": "3030-30852",
    "special": [
      {
        "value": "Sega CD Team Player compatible title",
        "forPlatform": {
          "name": "Sega CD",
          "id": "ccl15",
          "igdbId": 78,
          "gbId": 29,
          "gbGuid": "3045-29",
          "tgdbId": 21
        }
      }
    ],
    "isExclusive": false,
    "isLaunchTitle": false
  },
  {
    "name": "Eternal Champions: Challenge from the Dark Side",
    "details": [
      "Sega CD exclusive"
    ],
    "id": "scd16",
    "igdbId": 5383,
    "gbId": 8021,
    "gbGuid": "3030-8021",
    "tgdbId": 5010,
    "isExclusive": [
      {
        "name": "Sega CD",
        "id": "ccl15",
        "igdbId": 78,
        "gbId": 29,
        "gbGuid": "3045-29",
        "tgdbId": 21
      }
    ],
    "isLaunchTitle": false,
    "special": []
  },
  {
    "name": "Formula One World Championship: Beyond the Limit",
    "details": [
      "Sega CD exclusive"
    ],
    "id": "scd17",
    "igdbId": 5388,
    "gbId": 7432,
    "gbGuid": "3030-7432",
    "tgdbId": 5012,
    "isExclusive": [
      {
        "name": "Sega CD",
        "id": "ccl15",
        "igdbId": 78,
        "gbId": 29,
        "gbGuid": "3045-29",
        "tgdbId": 21
      }
    ],
    "isLaunchTitle": false,
    "special": []
  },
  {
    "name": "Ground Zero: Texas",
    "details": [
      "Sega CD exclusive"
    ],
    "id": "scd18",
    "igdbId": 5390,
    "gbId": 20309,
    "gbGuid": "3030-20309",
    "tgdbId": 5018,
    "isExclusive": [
      {
        "name": "Sega CD",
        "id": "ccl15",
        "igdbId": 78,
        "gbId": 29,
        "gbGuid": "3045-29",
        "tgdbId": 21
      }
    ],
    "isLaunchTitle": false,
    "special": []
  },
  {
    "name": "Heart of the Alien: Out of this World Parts I And II",
    "details": [
      "Sega CD exclusive"
    ],
    "id": "scd19",
    "igdbId": 46420,
    "gbId": 17785,
    "gbGuid": "3030-17785",
    "tgdbId": 5019,
    "isExclusive": [
      {
        "name": "Sega CD",
        "id": "ccl15",
        "igdbId": 78,
        "gbId": 29,
        "gbGuid": "3045-29",
        "tgdbId": 21
      }
    ],
    "isLaunchTitle": false,
    "special": []
  },
  {
    "name": "INXS: Make My Video",
    "id": "scd20",
    "details": [
      "Sega CD launch title",
      "Sega CD exclusive"
    ],
    "igdbId": 46418,
    "gbId": 10517,
    "gbGuid": "3030-10517",
    "tgdbId": 5057,
    "isLaunchTitle": [
      {
        "name": "Sega CD",
        "id": "ccl15",
        "igdbId": 78,
        "gbId": 29,
        "gbGuid": "3045-29",
        "tgdbId": 21
      }
    ],
    "isExclusive": [
      {
        "name": "Sega CD",
        "id": "ccl15",
        "igdbId": 78,
        "gbId": 29,
        "gbGuid": "3045-29",
        "tgdbId": 21
      }
    ],
    "special": []
  },
  {
    "name": "Jurassic Park",
    "details": [
      "Sega CD exclusive"
    ],
    "id": "scd21",
    "igdbId": 4519,
    "gbId": 21383,
    "gbGuid": "3030-21383",
    "tgdbId": 537,
    "isExclusive": [
      {
        "name": "Sega CD",
        "id": "ccl15",
        "igdbId": 78,
        "gbId": 29,
        "gbGuid": "3045-29",
        "tgdbId": 21
      }
    ],
    "isLaunchTitle": false,
    "special": []
  },
  {
    "name": "Keio Flying Squadron",
    "details": [
      "Sega CD exclusive"
    ],
    "id": "scd22",
    "igdbId": 12912,
    "gbId": 16410,
    "gbGuid": "3030-16410",
    "tgdbId": 2578,
    "isExclusive": [
      {
        "name": "Sega CD",
        "id": "ccl15",
        "igdbId": 78,
        "gbId": 29,
        "gbGuid": "3045-29",
        "tgdbId": 21
      }
    ],
    "isLaunchTitle": false,
    "special": []
  },
  {
    "name": "Kris Kross: Make My Video",
    "details": [
      "Sega CD exclusive"
    ],
    "id": "scd23",
    "igdbId": 46417,
    "gbId": 10670,
    "gbGuid": "3030-10670",
    "tgdbId": 5058,
    "isExclusive": [
      {
        "name": "Sega CD",
        "id": "ccl15",
        "igdbId": 78,
        "gbId": 29,
        "gbGuid": "3045-29",
        "tgdbId": 21
      }
    ],
    "isLaunchTitle": false,
    "special": []
  },
  {
    "name": "Lunar: The Silver Star",
    "details": [
      "Sega CD exclusive"
    ],
    "id": "scd24",
    "igdbId": 5334,
    "gbId": 13562,
    "gbGuid": "3030-13562",
    "tgdbId": 5054,
    "isExclusive": [
      {
        "name": "Sega CD",
        "id": "ccl15",
        "igdbId": 78,
        "gbId": 29,
        "gbGuid": "3045-29",
        "tgdbId": 21
      }
    ],
    "isLaunchTitle": false,
    "special": []
  },
  {
    "name": "Marky Mark and the Funky Bunch: Make My Video",
    "id": "scd25",
    "details": [
      "Sega CD launch title",
      "Sega CD exclusive"
    ],
    "igdbId": 46416,
    "gbId": 5307,
    "gbGuid": "3030-5307",
    "tgdbId": null,
    "isLaunchTitle": [
      {
        "name": "Sega CD",
        "id": "ccl15",
        "igdbId": 78,
        "gbId": 29,
        "gbGuid": "3045-29",
        "tgdbId": 21
      }
    ],
    "isExclusive": [
      {
        "name": "Sega CD",
        "id": "ccl15",
        "igdbId": 78,
        "gbId": 29,
        "gbGuid": "3045-29",
        "tgdbId": 21
      }
    ],
    "special": []
  },
  {
    "name": "Midnight Raiders",
    "details": [
      "Sega CD exclusive"
    ],
    "id": "scd26",
    "igdbId": 19743,
    "gbId": 16280,
    "gbGuid": "3030-16280",
    "tgdbId": 5064,
    "isExclusive": [
      {
        "name": "Sega CD",
        "id": "ccl15",
        "igdbId": 78,
        "gbId": 29,
        "gbGuid": "3045-29",
        "tgdbId": 21
      }
    ],
    "isLaunchTitle": false,
    "special": []
  },
  {
    "name": "Mighty Mighty Missile!",
    "id": "scd27",
    "details": [
      "Sega CD Team Player compatible title"
    ],
    "igdbId": 128890,
    "gbId": null,
    "gbGuid": null,
    "special": [
      {
        "value": "Sega CD Team Player compatible title",
        "forPlatform": {
          "name": "Sega CD",
          "id": "ccl15",
          "igdbId": 78,
          "gbId": 29,
          "gbGuid": "3045-29",
          "tgdbId": 21
        }
      }
    ],
    "isExclusive": false,
    "isLaunchTitle": false
  },
  {
    "name": "Mighty Morphin Power Rangers",
    "details": [
      "Sega CD exclusive"
    ],
    "id": "scd28",
    "igdbId": 3286,
    "gbId": 27002,
    "gbGuid": "3030-27002",
    "tgdbId": 439,
    "isExclusive": [
      {
        "name": "Sega CD",
        "id": "ccl15",
        "igdbId": 78,
        "gbId": 29,
        "gbGuid": "3045-29",
        "tgdbId": 21
      }
    ],
    "isLaunchTitle": false,
    "special": []
  },
  {
    "name": "NBA Jam",
    "id": "scd29",
    "details": [
      "Sega CD Team Player compatible title"
    ],
    "igdbId": 8995,
    "gbId": 16928,
    "gbGuid": "3030-16928",
    "special": [
      {
        "value": "Sega CD Team Player compatible title",
        "forPlatform": {
          "name": "Sega CD",
          "id": "ccl15",
          "igdbId": 78,
          "gbId": 29,
          "gbGuid": "3045-29",
          "tgdbId": 21
        }
      }
    ],
    "isExclusive": false,
    "isLaunchTitle": false
  },
  {
    "name": "Night Trap",
    "id": "scd30",
    "details": [
      "Sega CD launch title"
    ],
    "igdbId": 2486,
    "gbId": 18648,
    "gbGuid": "3030-18648",
    "tgdbId": 5071,
    "isLaunchTitle": [
      {
        "name": "Sega CD",
        "id": "ccl15",
        "igdbId": 78,
        "gbId": 29,
        "gbGuid": "3045-29",
        "tgdbId": 21
      }
    ],
    "isExclusive": false,
    "special": []
  },
  {
    "name": "Power Factory Featuring C+C Music Factory",
    "details": [
      "Sega CD exclusive"
    ],
    "id": "scd31",
    "igdbId": 5420,
    "gbId": 18613,
    "gbGuid": "3030-18613",
    "tgdbId": 5076,
    "isExclusive": [
      {
        "name": "Sega CD",
        "id": "ccl15",
        "igdbId": 78,
        "gbId": 29,
        "gbGuid": "3045-29",
        "tgdbId": 21
      }
    ],
    "isLaunchTitle": false,
    "special": []
  },
  {
    "name": "Prize Fighter",
    "details": [
      "Sega CD exclusive"
    ],
    "id": "scd32",
    "igdbId": 5424,
    "gbId": 8564,
    "gbGuid": "3030-8564",
    "tgdbId": 5079,
    "isExclusive": [
      {
        "name": "Sega CD",
        "id": "ccl15",
        "igdbId": 78,
        "gbId": 29,
        "gbGuid": "3045-29",
        "tgdbId": 21
      }
    ],
    "isLaunchTitle": false,
    "special": []
  },
  {
    "name": "RDF Global Conflict",
    "details": [
      "Sega CD exclusive"
    ],
    "id": "scd33",
    "igdbId": 46606,
    "gbId": null,
    "gbGuid": null,
    "tgdbId": 5082,
    "isExclusive": [
      {
        "name": "Sega CD",
        "id": "ccl15",
        "igdbId": 78,
        "gbId": 29,
        "gbGuid": "3045-29",
        "tgdbId": 21
      }
    ],
    "isLaunchTitle": false,
    "special": []
  },
  {
    "name": "Racing Aces",
    "details": [
      "Sega CD exclusive"
    ],
    "id": "scd34",
    "igdbId": 5426,
    "gbId": 14317,
    "gbGuid": "3030-14317",
    "tgdbId": 444,
    "isExclusive": [
      {
        "name": "Sega CD",
        "id": "ccl15",
        "igdbId": 78,
        "gbId": 29,
        "gbGuid": "3045-29",
        "tgdbId": 21
      }
    ],
    "isLaunchTitle": false,
    "special": []
  },
  {
    "name": "Robo Aleste",
    "details": [
      "Sega CD exclusive"
    ],
    "id": "scd35",
    "igdbId": 5430,
    "gbId": 12066,
    "gbGuid": "3030-12066",
    "tgdbId": 445,
    "isExclusive": [
      {
        "name": "Sega CD",
        "id": "ccl15",
        "igdbId": 78,
        "gbId": 29,
        "gbGuid": "3045-29",
        "tgdbId": 21
      }
    ],
    "isLaunchTitle": false,
    "special": []
  },
  {
    "name": "Sega Classics Arcade Collection 4-in-1",
    "id": "scd36",
    "details": [
      "Sega CD launch title",
      "Sega CD exclusive"
    ],
    "igdbId": 5432,
    "gbId": 43485,
    "gbGuid": "3030-43485",
    "tgdbId": 29399,
    "isLaunchTitle": [
      {
        "name": "Sega CD",
        "id": "ccl15",
        "igdbId": 78,
        "gbId": 29,
        "gbGuid": "3045-29",
        "tgdbId": 21
      }
    ],
    "isExclusive": [
      {
        "name": "Sega CD",
        "id": "ccl15",
        "igdbId": 78,
        "gbId": 29,
        "gbGuid": "3045-29",
        "tgdbId": 21
      }
    ],
    "special": []
  },
  {
    "name": "Sewer Shark",
    "id": "scd37",
    "details": [
      "Sega CD launch title"
    ],
    "igdbId": 4293,
    "gbId": 7427,
    "gbGuid": "3030-7427",
    "tgdbId": 739,
    "isLaunchTitle": [
      {
        "name": "Sega CD",
        "id": "ccl15",
        "igdbId": 78,
        "gbId": 29,
        "gbGuid": "3045-29",
        "tgdbId": 21
      }
    ],
    "isExclusive": false,
    "special": []
  },
  {
    "name": "Shadowrun",
    "details": [
      "Sega CD exclusive"
    ],
    "id": "scd38",
    "igdbId": 78514,
    "gbId": 34672,
    "gbGuid": "3030-34672",
    "tgdbId": 1306,
    "isExclusive": [
      {
        "name": "Sega CD",
        "id": "ccl15",
        "igdbId": 78,
        "gbId": 29,
        "gbGuid": "3045-29",
        "tgdbId": 21
      }
    ],
    "isLaunchTitle": false,
    "special": []
  },
  {
    "name": "Sherlock Holmes Consulting Detective",
    "id": "scd39",
    "details": [
      "Sega CD launch title"
    ],
    "igdbId": 5435,
    "gbId": 12998,
    "gbGuid": "3030-12998",
    "tgdbId": 42989,
    "isLaunchTitle": [
      {
        "name": "Sega CD",
        "id": "ccl15",
        "igdbId": 78,
        "gbId": 29,
        "gbGuid": "3045-29",
        "tgdbId": 21
      }
    ],
    "isExclusive": false,
    "special": []
  },
  {
    "name": "Shining Force CD",
    "details": [
      "Sega CD exclusive"
    ],
    "id": "scd40",
    "igdbId": 3198,
    "gbId": 16383,
    "gbGuid": "3030-16383",
    "tgdbId": 5092,
    "isExclusive": [
      {
        "name": "Sega CD",
        "id": "ccl15",
        "igdbId": 78,
        "gbId": 29,
        "gbGuid": "3045-29",
        "tgdbId": 21
      }
    ],
    "isLaunchTitle": false,
    "special": []
  },
  {
    "name": "Sol-Feace",
    "id": "scd41",
    "details": [
      "Sega CD launch title"
    ],
    "igdbId": 4388,
    "gbId": 2685,
    "gbGuid": "3030-2685",
    "tgdbId": 5096,
    "isLaunchTitle": [
      {
        "name": "Sega CD",
        "id": "ccl15",
        "igdbId": 78,
        "gbId": 29,
        "gbGuid": "3045-29",
        "tgdbId": 21
      }
    ],
    "isExclusive": false,
    "special": []
  },
  {
    "name": "Soulstar",
    "details": [
      "Sega CD exclusive"
    ],
    "id": "scd42",
    "igdbId": 5453,
    "gbId": 15595,
    "gbGuid": "3030-15595",
    "tgdbId": 5266,
    "isExclusive": [
      {
        "name": "Sega CD",
        "id": "ccl15",
        "igdbId": 78,
        "gbId": 29,
        "gbGuid": "3045-29",
        "tgdbId": 21
      }
    ],
    "isLaunchTitle": false,
    "special": []
  },
  {
    "name": "The Adventures of Batman & Robin",
    "details": [
      "Sega CD exclusive"
    ],
    "id": "scd43",
    "igdbId": 5346,
    "gbId": 12434,
    "gbGuid": "3030-12434",
    "tgdbId": 1049,
    "isExclusive": [
      {
        "name": "Sega CD",
        "id": "ccl15",
        "igdbId": 78,
        "gbId": 29,
        "gbGuid": "3045-29",
        "tgdbId": 21
      }
    ],
    "isLaunchTitle": false,
    "special": []
  },
  {
    "name": "The Masked Rider: Kamen Rider ZO",
    "details": [
      "Sega CD exclusive"
    ],
    "id": "scd44",
    "igdbId": 46409,
    "gbId": 15630,
    "gbGuid": "3030-15630",
    "tgdbId": 5106,
    "isExclusive": [
      {
        "name": "Sega CD",
        "id": "ccl15",
        "igdbId": 78,
        "gbId": 29,
        "gbGuid": "3045-29",
        "tgdbId": 21
      }
    ],
    "isLaunchTitle": false,
    "special": []
  },
  {
    "name": "Third World War",
    "details": [
      "Sega CD exclusive"
    ],
    "id": "scd45",
    "igdbId": 5457,
    "gbId": 40982,
    "gbGuid": "3030-40982",
    "tgdbId": 5109,
    "isExclusive": [
      {
        "name": "Sega CD",
        "id": "ccl15",
        "igdbId": 78,
        "gbId": 29,
        "gbGuid": "3045-29",
        "tgdbId": 21
      }
    ],
    "isLaunchTitle": false,
    "special": []
  },
  {
    "name": "WWF Rage in the Cage",
    "details": [
      "Sega CD exclusive"
    ],
    "id": "scd46",
    "igdbId": 5465,
    "gbId": 22268,
    "gbGuid": "3030-22268",
    "tgdbId": 5123,
    "isExclusive": [
      {
        "name": "Sega CD",
        "id": "ccl15",
        "igdbId": 78,
        "gbId": 29,
        "gbGuid": "3045-29",
        "tgdbId": 21
      }
    ],
    "isLaunchTitle": false,
    "special": []
  },
  {
    "name": "Wild Woody",
    "details": [
      "Sega CD exclusive"
    ],
    "id": "scd47",
    "igdbId": 5461,
    "gbId": 20438,
    "gbGuid": "3030-20438",
    "tgdbId": 5116,
    "isExclusive": [
      {
        "name": "Sega CD",
        "id": "ccl15",
        "igdbId": 78,
        "gbId": 29,
        "gbGuid": "3045-29",
        "tgdbId": 21
      }
    ],
    "isLaunchTitle": false,
    "special": []
  },
  {
    "name": "Wirehead",
    "details": [
      "Sega CD exclusive"
    ],
    "id": "scd48",
    "igdbId": 5462,
    "gbId": 5705,
    "gbGuid": "3030-5705",
    "tgdbId": 5119,
    "isExclusive": [
      {
        "name": "Sega CD",
        "id": "ccl15",
        "igdbId": 78,
        "gbId": 29,
        "gbGuid": "3045-29",
        "tgdbId": 21
      }
    ],
    "isLaunchTitle": false,
    "special": []
  },
  {
    "name": "World Cup USA '94",
    "id": "scd49",
    "details": [
      "Sega CD Team Player compatible title"
    ],
    "igdbId": 5464,
    "gbId": 5498,
    "gbGuid": "3030-5498",
    "special": [
      {
        "value": "Sega CD Team Player compatible title",
        "forPlatform": {
          "name": "Sega CD",
          "id": "ccl15",
          "igdbId": 78,
          "gbId": 29,
          "gbGuid": "3045-29",
          "tgdbId": 21
        }
      }
    ],
    "isExclusive": false,
    "isLaunchTitle": false
  }
]