[
  {
    "name": "Bakukyuu Renpatsu!! Super B-Daman",
    "id": "snessm1",
    "details": "SNES Super Multitap compatible title",
    "igdbId": 42520,
    "gbId": 59797,
    "gbGuid": "3030-59797",
    "category": "multiplayer"
  },
  {
    "name": "Bakutou Dodgers",
    "id": "snessm2",
    "details": "SNES Super Multitap compatible title",
    "igdbId": 44449,
    "gbId": null,
    "gbGuid": null,
    "category": "multiplayer"
  },
  {
    "name": "Barkley: Shut Up and Jam!",
    "id": "snessm3",
    "details": "SNES Super Multitap compatible title",
    "igdbId": 4520,
    "gbId": 11891,
    "gbGuid": "3030-11891",
    "category": "multiplayer"
  },
  {
    "name": "Battle Cross",
    "id": "snessm4",
    "details": "SNES Super Multitap compatible title",
    "igdbId": 95412,
    "gbId": 37539,
    "gbGuid": "3030-37539",
    "category": "multiplayer"
  },
  {
    "name": "Battle jockey",
    "id": "snessm5",
    "details": "SNES Super Multitap compatible title",
    "igdbId": 44425,
    "gbId": 50705,
    "gbGuid": "3030-50705",
    "category": "multiplayer"
  },
  {
    "name": "Bill Walsh College Football",
    "id": "snessm6",
    "details": "SNES Super Multitap compatible title",
    "igdbId": 5363,
    "gbId": 27133,
    "gbGuid": "3030-27133",
    "category": "multiplayer"
  },
  {
    "name": "Capcom's Soccer Shootout",
    "id": "snessm7",
    "details": "SNES Super Multitap compatible title",
    "igdbId": 42598,
    "gbId": 25661,
    "gbGuid": "3030-25661",
    "category": "multiplayer"
  },
  {
    "name": "College Slam",
    "id": "snessm8",
    "details": "SNES Super Multitap compatible title",
    "igdbId": 4541,
    "gbId": 125,
    "gbGuid": "3030-125",
    "category": "multiplayer"
  },
  {
    "name": "Crystal Beans: From Dungeon Explorer",
    "id": "snessm9",
    "details": "SNES Super Multitap compatible title",
    "igdbId": 16297,
    "gbId": 18216,
    "gbGuid": "3030-18216",
    "category": "multiplayer"
  },
  {
    "name": "Dragon: The Bruce Lee Story",
    "id": "snessm10",
    "details": "SNES Super Multitap compatible title",
    "igdbId": 18617,
    "gbId": 11980,
    "gbGuid": "3030-11980",
    "category": "multiplayer"
  },
  {
    "name": "Dream Basketball: Dunk & Hoop",
    "id": "snessm11",
    "details": "SNES Super Multitap compatible title",
    "igdbId": 42279,
    "gbId": 50450,
    "gbGuid": "3030-50450",
    "category": "multiplayer"
  },
  {
    "name": "Dynamic Stadium",
    "id": "snessm12",
    "details": "SNES Super Multitap compatible title",
    "igdbId": 42278,
    "gbId": 47480,
    "gbGuid": "3030-47480",
    "category": "multiplayer"
  },
  {
    "name": "ESPN National Hockey Night",
    "id": "snessm13",
    "details": "SNES Super Multitap compatible title",
    "igdbId": 5381,
    "gbId": 30852,
    "gbGuid": "3030-30852",
    "category": "multiplayer"
  },
  {
    "name": "FIFA: Road to World Cup 98",
    "id": "snessm14",
    "details": "SNES Super Multitap compatible title",
    "igdbId": 705,
    "gbId": 11207,
    "gbGuid": "3030-11207",
    "category": "multiplayer"
  },
  {
    "name": "FIFA International Soccer",
    "id": "snessm15",
    "details": "SNES Super Multitap compatible title",
    "igdbId": 4345,
    "gbId": 6260,
    "gbGuid": "3030-6260",
    "category": "multiplayer"
  },
  {
    "name": "FIFA Soccer 96",
    "id": "snessm16",
    "details": "SNES Super Multitap compatible title",
    "igdbId": 704,
    "gbId": 14524,
    "gbGuid": "3030-14524",
    "category": "multiplayer"
  },
  {
    "name": "FIFA Soccer 97",
    "id": "snessm17",
    "details": "SNES Super Multitap compatible title",
    "igdbId": 71398,
    "gbId": 3383,
    "gbGuid": "3030-3383",
    "category": "multiplayer"
  },
  {
    "name": "Final Set",
    "id": "snessm18",
    "details": "SNES Super Multitap compatible title",
    "igdbId": 44430,
    "gbId": 46955,
    "gbGuid": "3030-46955",
    "category": "multiplayer"
  },
  {
    "name": "Firestriker",
    "id": "snessm19",
    "details": "SNES Super Multitap compatible title",
    "igdbId": 42553,
    "gbId": 7528,
    "gbGuid": "3030-7528",
    "category": "multiplayer"
  },
  {
    "name": "From TV Animation: Slam Dunk SD Heat Up!!",
    "id": "snessm20",
    "details": "SNES Super Multitap compatible title",
    "igdbId": 65608,
    "gbId": 36646,
    "gbGuid": "3030-36646",
    "category": "multiplayer"
  },
  {
    "name": "Go! Go! Dodge League",
    "id": "snessm21",
    "details": "SNES Super Multitap compatible title",
    "igdbId": 42274,
    "gbId": 32142,
    "gbGuid": "3030-32142",
    "category": "multiplayer"
  },
  {
    "name": "Hammerlock Wrestling",
    "id": "snessm22",
    "details": "SNES Super Multitap compatible title",
    "igdbId": 42589,
    "gbId": 38662,
    "gbGuid": "3030-38662",
    "category": "multiplayer"
  },
  {
    "name": "Hat Trick Hero 2",
    "id": "snessm23",
    "details": "SNES Super Multitap compatible title",
    "igdbId": 38332,
    "gbId": 37195,
    "gbGuid": "3030-37195",
    "category": "multiplayer"
  },
  {
    "name": "Head-On Soccer",
    "id": "snessm24",
    "details": "SNES Super Multitap compatible title",
    "igdbId": 19758,
    "gbId": 12463,
    "gbGuid": "3030-12463",
    "category": "multiplayer"
  },
  {
    "name": "Hebereke no Oishii Puzzle wa Irimasenka",
    "id": "snessm25",
    "details": "SNES Super Multitap compatible title",
    "igdbId": 38007,
    "gbId": 49749,
    "gbGuid": "3030-49749",
    "category": "multiplayer"
  },
  {
    "name": "Human Grand Prix III: F1 Triple Battle",
    "id": "snessm26",
    "details": "SNES Super Multitap compatible title",
    "igdbId": 38172,
    "gbId": 39262,
    "gbGuid": "3030-39262",
    "category": "multiplayer"
  },
  {
    "name": "Human Grand Prix IV: F1 Dream Battle",
    "id": "snessm27",
    "details": "SNES Super Multitap compatible title",
    "igdbId": 38171,
    "gbId": 39263,
    "gbGuid": "3030-39263",
    "category": "multiplayer"
  },
  {
    "name": "Hungry Dinosaurs",
    "id": "snessm28",
    "details": "SNES Super Multitap compatible title",
    "igdbId": 42587,
    "gbId": 38487,
    "gbGuid": "3030-38487",
    "category": "multiplayer"
  },
  {
    "name": "International Superstar Soccer Deluxe",
    "id": "snessm29",
    "details": "SNES Super Multitap compatible title",
    "igdbId": 9862,
    "gbId": 7025,
    "gbGuid": "3030-7025",
    "category": "multiplayer"
  },
  {
    "name": "J. League Excite Stage '94",
    "id": "snessm30",
    "details": "SNES Super Multitap compatible title",
    "igdbId": null,
    "gbId": null,
    "gbGuid": null,
    "category": "multiplayer"
  },
  {
    "name": "J. League Excite Stage '95",
    "id": "snessm31",
    "details": "SNES Super Multitap compatible title",
    "igdbId": null,
    "gbId": null,
    "gbGuid": null,
    "category": "multiplayer"
  },
  {
    "name": "J. League Excite Stage '96",
    "id": "snessm32",
    "details": "SNES Super Multitap compatible title",
    "igdbId": null,
    "gbId": null,
    "gbGuid": null,
    "category": "multiplayer"
  },
  {
    "name": "J. League Super Soccer '95",
    "id": "snessm33",
    "details": "SNES Super Multitap compatible title",
    "igdbId": null,
    "gbId": null,
    "gbGuid": null,
    "category": "multiplayer"
  },
  {
    "name": "J. League Super Soccer",
    "id": "snessm34",
    "details": "SNES Super Multitap compatible title",
    "igdbId": null,
    "gbId": null,
    "gbGuid": null,
    "category": "multiplayer"
  },
  {
    "name": "JWP Joshi Pro Wrestling: Pure Wrestle Queens",
    "id": "snessm35",
    "details": "SNES Super Multitap compatible title",
    "igdbId": 38276,
    "gbId": 28212,
    "gbGuid": "3030-28212",
    "category": "multiplayer"
  },
  {
    "name": "Jikkyou Power Pro Wrestling '96: Max Voltage",
    "id": "snessm36",
    "details": "SNES Super Multitap compatible title",
    "igdbId": 42415,
    "gbId": 28186,
    "gbGuid": "3030-28186",
    "category": "multiplayer"
  },
  {
    "name": "Jimmy Connors Pro Tennis Tour",
    "id": "snessm37",
    "details": "SNES Super Multitap compatible title",
    "igdbId": 42605,
    "gbId": 5740,
    "gbGuid": "3030-5740",
    "category": "multiplayer"
  },
  {
    "name": "Kunio-Kun no Dodge Ball Dayo Zenin Shuugo!",
    "id": "snessm38",
    "details": "SNES Super Multitap compatible title",
    "igdbId": 42516,
    "gbId": 950,
    "gbGuid": "3030-950",
    "category": "multiplayer"
  },
  {
    "name": "Looney Tunes B-Ball",
    "id": "snessm39",
    "details": "SNES Super Multitap compatible title",
    "igdbId": 42585,
    "gbId": null,
    "gbGuid": null,
    "category": "multiplayer"
  },
  {
    "name": "Madden NFL '94",
    "id": "snessm40",
    "details": "SNES Super Multitap compatible title",
    "igdbId": 4381,
    "gbId": 7106,
    "gbGuid": "3030-7106",
    "category": "multiplayer"
  },
  {
    "name": "Madden NFL 95",
    "id": "snessm41",
    "details": "SNES Super Multitap compatible title",
    "igdbId": 4506,
    "gbId": 7715,
    "gbGuid": "3030-7715",
    "category": "multiplayer"
  },
  {
    "name": "Madden NFL 96",
    "id": "snessm42",
    "details": "SNES Super Multitap compatible title",
    "igdbId": 4542,
    "gbId": 12957,
    "gbGuid": "3030-12957",
    "category": "multiplayer"
  },
  {
    "name": "Madden NFL 97",
    "id": "snessm43",
    "details": "SNES Super Multitap compatible title",
    "igdbId": 4589,
    "gbId": 6279,
    "gbGuid": "3030-6279",
    "category": "multiplayer"
  },
  {
    "name": "Madden NFL 98",
    "id": "snessm44",
    "details": "SNES Super Multitap compatible title",
    "igdbId": 4590,
    "gbId": 8679,
    "gbGuid": "3030-8679",
    "category": "multiplayer"
  },
  {
    "name": "Micro Machines 2: Turbo Tournament",
    "id": "snessm45",
    "details": "SNES Super Multitap compatible title",
    "igdbId": 8775,
    "gbId": 20350,
    "gbGuid": "3030-20350",
    "category": "multiplayer"
  },
  {
    "name": "Micro Machines",
    "id": "snessm46",
    "details": "SNES Super Multitap compatible title",
    "igdbId": 2703,
    "gbId": 2140,
    "gbGuid": "3030-2140",
    "category": "multiplayer"
  },
  {
    "name": "Mizuki Shigeru no Youkai Hyakki Yakou",
    "id": "snessm47",
    "details": "SNES Super Multitap compatible title",
    "igdbId": 37924,
    "gbId": 28352,
    "gbGuid": "3030-28352",
    "category": "multiplayer"
  },
  {
    "name": "Multi Play Volleyball",
    "id": "snessm48",
    "details": "SNES Super Multitap compatible title",
    "igdbId": 38363,
    "gbId": 28365,
    "gbGuid": "3030-28365",
    "category": "multiplayer"
  },
  {
    "name": "NBA Give 'n Go",
    "id": "snessm49",
    "details": "SNES Super Multitap compatible title",
    "igdbId": 42482,
    "gbId": 11202,
    "gbGuid": "3030-11202",
    "category": "multiplayer"
  },
  {
    "name": "NBA Hangtime",
    "id": "snessm50",
    "details": "SNES Super Multitap compatible title",
    "igdbId": 3550,
    "gbId": 10512,
    "gbGuid": "3030-10512",
    "category": "multiplayer"
  },
  {
    "name": "NBA Jam Tournament Edition",
    "id": "snessm51",
    "details": "SNES Super Multitap compatible title",
    "igdbId": 19712,
    "gbId": 14792,
    "gbGuid": "3030-14792",
    "category": "multiplayer"
  },
  {
    "name": "NBA Jam",
    "id": "snessm52",
    "details": "SNES Super Multitap compatible title",
    "igdbId": 8995,
    "gbId": 16928,
    "gbGuid": "3030-16928",
    "category": "multiplayer"
  },
  {
    "name": "NBA Live 95",
    "id": "snessm53",
    "details": "SNES Super Multitap compatible title",
    "igdbId": 37285,
    "gbId": 3091,
    "gbGuid": "3030-3091",
    "category": "multiplayer"
  },
  {
    "name": "NBA Live 96",
    "id": "snessm54",
    "details": "SNES Super Multitap compatible title",
    "igdbId": 809,
    "gbId": 20257,
    "gbGuid": "3030-20257",
    "category": "multiplayer"
  },
  {
    "name": "NBA Live 97",
    "id": "snessm55",
    "details": "SNES Super Multitap compatible title",
    "igdbId": 20134,
    "gbId": 1356,
    "gbGuid": "3030-1356",
    "category": "multiplayer"
  },
  {
    "name": "NBA Live 98",
    "id": "snessm56",
    "details": "SNES Super Multitap compatible title",
    "igdbId": 26013,
    "gbId": 15170,
    "gbGuid": "3030-15170",
    "category": "multiplayer"
  },
  {
    "name": "NCAA Final Four Basketball",
    "id": "snessm57",
    "details": "SNES Super Multitap compatible title",
    "igdbId": 4385,
    "gbId": 52965,
    "gbGuid": "3030-52965",
    "category": "multiplayer"
  },
  {
    "name": "NCAA Football",
    "id": "snessm58",
    "details": "SNES Super Multitap compatible title",
    "igdbId": 46680,
    "gbId": 15972,
    "gbGuid": "3030-15972",
    "category": "multiplayer"
  },
  {
    "name": "NFL Quarterback Club 96",
    "id": "snessm59",
    "details": "SNES Super Multitap compatible title",
    "igdbId": 25080,
    "gbId": 11504,
    "gbGuid": "3030-11504",
    "category": "multiplayer"
  },
  {
    "name": "NFL Quarterback Club",
    "id": "snessm60",
    "details": "SNES Super Multitap compatible title",
    "igdbId": 114754,
    "gbId": 22136,
    "gbGuid": "3030-22136",
    "category": "multiplayer"
  },
  {
    "name": "NHL '94",
    "id": "snessm61",
    "details": "SNES Super Multitap compatible title",
    "igdbId": 5405,
    "gbId": 20166,
    "gbGuid": "3030-20166",
    "category": "multiplayer"
  },
  {
    "name": "NHL 98",
    "id": "snessm62",
    "details": "SNES Super Multitap compatible title",
    "igdbId": 818,
    "gbId": 18845,
    "gbGuid": "3030-18845",
    "category": "multiplayer"
  },
  {
    "name": "NHL Pro Hockey '94",
    "id": "snessm63",
    "details": "SNES Super Multitap compatible title",
    "igdbId": null,
    "gbId": null,
    "gbGuid": null,
    "category": "multiplayer"
  },
  {
    "name": "Natsume Championship Wrestling",
    "id": "snessm64",
    "details": "SNES Super Multitap compatible title",
    "igdbId": 42483,
    "gbId": 9816,
    "gbGuid": "3030-9816",
    "category": "multiplayer"
  },
  {
    "name": "The Peace Keepers",
    "id": "snessm65",
    "details": "SNES Super Multitap compatible title",
    "igdbId": 44465,
    "gbId": 7950,
    "gbGuid": "3030-7950",
    "category": "multiplayer"
  },
  {
    "name": "Pieces",
    "id": "snessm66",
    "details": "SNES Super Multitap compatible title",
    "igdbId": 46587,
    "gbId": 28172,
    "gbGuid": "3030-28172",
    "category": "multiplayer"
  },
  {
    "name": "Rap Jam: Volume One",
    "id": "snessm67",
    "details": "SNES Super Multitap compatible title",
    "igdbId": 44458,
    "gbId": 946,
    "gbGuid": "3030-946",
    "category": "multiplayer"
  },
  {
    "name": "Saturday Night Slam Masters",
    "id": "snessm68",
    "details": "SNES Super Multitap compatible title",
    "igdbId": 4504,
    "gbId": 16684,
    "gbGuid": "3030-16684",
    "category": "multiplayer"
  },
  {
    "name": "Secret of Mana",
    "id": "snessm69",
    "details": "SNES Super Multitap compatible title",
    "igdbId": 3216,
    "gbId": 19507,
    "gbGuid": "3030-19507",
    "category": "multiplayer"
  },
  {
    "name": "Shin Nippon Pro Wrestling '94: Battlefield in Tokyo Dome",
    "id": "snessm70",
    "details": "SNES Super Multitap compatible title",
    "igdbId": 61304,
    "gbId": 46993,
    "gbGuid": "3030-46993",
    "category": "multiplayer"
  },
  {
    "name": "Shin Nippon Pro Wrestling: Chou Senshi in Tokyo Dome",
    "id": "snessm71",
    "details": "SNES Super Multitap compatible title",
    "igdbId": 61317,
    "gbId": 46954,
    "gbGuid": "3030-46954",
    "category": "multiplayer"
  },
  {
    "name": "Shin Nippon Pro Wrestling '95: Tokyo Dome Battle 7",
    "id": "snessm72",
    "details": "SNES Super Multitap compatible title",
    "igdbId": 61303,
    "gbId": 46994,
    "gbGuid": "3030-46994",
    "category": "multiplayer"
  },
  {
    "name": "Super Family Tennis",
    "id": "snessm73",
    "details": "SNES Super Multitap compatible title",
    "igdbId": 44106,
    "gbId": 23133,
    "gbGuid": "3030-23133",
    "category": "multiplayer"
  },
  {
    "name": "The Sporting News Baseball",
    "id": "snessm74",
    "details": "SNES Super Multitap compatible title",
    "igdbId": 55154,
    "gbId": 38050,
    "gbGuid": "3030-38050",
    "category": "multiplayer"
  },
  {
    "name": "Sterling Sharpe: End 2 End",
    "id": "snessm75",
    "details": "SNES Super Multitap compatible title",
    "igdbId": 38434,
    "gbId": 43476,
    "gbGuid": "3030-43476",
    "category": "multiplayer"
  },
  {
    "name": "Street Hockey '95",
    "id": "snessm76",
    "details": "SNES Super Multitap compatible title",
    "igdbId": 38431,
    "gbId": 23132,
    "gbGuid": "3030-23132",
    "category": "multiplayer"
  },
  {
    "name": "Street Racer",
    "id": "snessm77",
    "details": "SNES Super Multitap compatible title",
    "igdbId": 19770,
    "gbId": 22190,
    "gbGuid": "3030-22190",
    "category": "multiplayer"
  },
  {
    "name": "Sugoi Hebereke",
    "id": "snessm78",
    "details": "SNES Super Multitap compatible title",
    "igdbId": 37846,
    "gbId": 38021,
    "gbGuid": "3030-38021",
    "category": "multiplayer"
  },
  {
    "name": "Sugoro Quest++ Dicenics",
    "id": "snessm79",
    "details": "SNES Super Multitap compatible title",
    "igdbId": 37807,
    "gbId": 38665,
    "gbGuid": "3030-38665",
    "category": "multiplayer"
  },
  {
    "name": "Super Bomberman: Panic Bomber W",
    "id": "snessm80",
    "details": "SNES Super Multitap compatible title",
    "igdbId": 42546,
    "gbId": null,
    "gbGuid": null,
    "category": "multiplayer"
  },
  {
    "name": "Super Bomberman 2",
    "id": "snessm81",
    "details": "SNES Super Multitap compatible title",
    "igdbId": 14530,
    "gbId": 12414,
    "gbGuid": "3030-12414",
    "category": "multiplayer"
  },
  {
    "name": "Super Bomberman 3",
    "id": "snessm82",
    "details": "SNES Super Multitap compatible title",
    "igdbId": 18618,
    "gbId": 7190,
    "gbGuid": "3030-7190",
    "category": "multiplayer"
  },
  {
    "name": "Super Bomberman 4",
    "id": "snessm83",
    "details": "SNES Super Multitap compatible title",
    "igdbId": 80539,
    "gbId": 10163,
    "gbGuid": "3030-10163",
    "category": "multiplayer"
  },
  {
    "name": "Super Bomberman 5",
    "id": "snessm84",
    "details": "SNES Super Multitap compatible title",
    "igdbId": 38387,
    "gbId": 3354,
    "gbGuid": "3030-3354",
    "category": "multiplayer"
  },
  {
    "name": "Super Bomberman",
    "id": "snessm85",
    "details": "SNES Super Multitap compatible title",
    "igdbId": 3450,
    "gbId": 11992,
    "gbGuid": "3030-11992",
    "category": "multiplayer"
  },
  {
    "name": "Super Fire Pro Wrestling: Queen's Special",
    "id": "snessm86",
    "details": "SNES Super Multitap compatible title",
    "igdbId": 38282,
    "gbId": 11265,
    "gbGuid": "3030-11265",
    "category": "multiplayer"
  },
  {
    "name": "Super Fire Pro Wrestling Special",
    "id": "snessm87",
    "details": "SNES Super Multitap compatible title",
    "igdbId": 38286,
    "gbId": 38888,
    "gbGuid": "3030-38888",
    "category": "multiplayer"
  },
  {
    "name": "Super Fire Pro Wrestling X Premium",
    "id": "snessm88",
    "details": "SNES Super Multitap compatible title",
    "igdbId": 38420,
    "gbId": null,
    "gbGuid": null,
    "category": "multiplayer"
  },
  {
    "name": "Super Fire Pro Wrestling X",
    "id": "snessm89",
    "details": "SNES Super Multitap compatible title",
    "igdbId": 38287,
    "gbId": 55330,
    "gbGuid": "3030-55330",
    "category": "multiplayer"
  },
  {
    "name": "Super Formation Soccer 94: World Cup Final Data",
    "id": "snessm90",
    "details": "SNES Super Multitap compatible title",
    "igdbId": 42361,
    "gbId": null,
    "gbGuid": null,
    "category": "multiplayer"
  },
  {
    "name": "Super Formation Soccer 94",
    "id": "snessm91",
    "details": "SNES Super Multitap compatible title",
    "igdbId": 42362,
    "gbId": 39323,
    "gbGuid": "3030-39323",
    "category": "multiplayer"
  },
  {
    "name": "Super Formation Soccer 95: della Serie A",
    "id": "snessm92",
    "details": "SNES Super Multitap compatible title",
    "igdbId": 42360,
    "gbId": 37247,
    "gbGuid": "3030-37247",
    "category": "multiplayer"
  },
  {
    "name": "Super Formation Soccer 96: World Club Edition",
    "id": "snessm94",
    "details": "SNES Super Multitap compatible title",
    "igdbId": 42359,
    "gbId": 40164,
    "gbGuid": "3030-40164",
    "category": "multiplayer"
  },
  {
    "name": "Super Formation Soccer II",
    "id": "snessm95",
    "details": "SNES Super Multitap compatible title",
    "igdbId": 42363,
    "gbId": 46495,
    "gbGuid": "3030-46495",
    "category": "multiplayer"
  },
  {
    "name": "Super Ice Hockey",
    "id": "snessm96",
    "details": "SNES Super Multitap compatible title",
    "igdbId": 38196,
    "gbId": 49294,
    "gbGuid": "3030-49294",
    "category": "multiplayer"
  },
  {
    "name": "Super Kyousouba: Kaze no Silpheed",
    "id": "snessm97",
    "details": "SNES Super Multitap compatible title",
    "igdbId": 37818,
    "gbId": 47229,
    "gbGuid": "3030-47229",
    "category": "multiplayer"
  },
  {
    "name": "Super Power League",
    "id": "snessm98",
    "details": "SNES Super Multitap compatible title",
    "igdbId": 42263,
    "gbId": 46678,
    "gbGuid": "3030-46678",
    "category": "multiplayer"
  },
  {
    "name": "Super Tekkyuu Fight!",
    "id": "snessm99",
    "details": "SNES Super Multitap compatible title",
    "igdbId": null,
    "gbId": 35226,
    "gbGuid": "3030-35226",
    "category": "multiplayer"
  },
  {
    "name": "Super Tetris 3",
    "id": "snessm100",
    "details": "SNES Super Multitap compatible title",
    "igdbId": 42531,
    "gbId": 30711,
    "gbGuid": "3030-30711",
    "category": "multiplayer"
  },
  {
    "name": "Syndicate",
    "id": "snessm101",
    "details": "SNES Super Multitap compatible title",
    "igdbId": 49,
    "gbId": 10865,
    "gbGuid": "3030-10865",
    "category": "multiplayer"
  },
  {
    "name": "Tenryu Genichiro no Pro Wrestling Revolution",
    "id": "snessm102",
    "details": "SNES Super Multitap compatible title",
    "igdbId": 38228,
    "gbId": null,
    "gbGuid": null,
    "category": "multiplayer"
  },
  {
    "name": "Tiny Toon Adventures: Wacky Sports Challenge",
    "id": "snessm103",
    "details": "SNES Super Multitap compatible title",
    "igdbId": 8051,
    "gbId": 15537,
    "gbGuid": "3030-15537",
    "category": "multiplayer"
  },
  {
    "name": "Top Gear 3000",
    "id": "snessm104",
    "details": "SNES Super Multitap compatible title",
    "igdbId": 46007,
    "gbId": 3215,
    "gbGuid": "3030-3215",
    "category": "multiplayer"
  },
  {
    "name": "Hanna Barbera's Turbo Toons",
    "id": "snessm105",
    "details": "SNES Super Multitap compatible title",
    "igdbId": 42619,
    "gbId": 50821,
    "gbGuid": "3030-50821",
    "category": "multiplayer"
  },
  {
    "name": "Virtual Soccer",
    "id": "snessm106",
    "details": "SNES Super Multitap compatible title",
    "igdbId": 46005,
    "gbId": 28166,
    "gbGuid": "3030-28166",
    "category": "multiplayer"
  },
  {
    "name": "Vs. Collection",
    "id": "snessm107",
    "details": "SNES Super Multitap compatible title",
    "igdbId": 37771,
    "gbId": 58983,
    "gbGuid": "3030-58983",
    "category": "multiplayer"
  },
  {
    "name": "WWF Raw",
    "id": "snessm108",
    "details": "SNES Super Multitap compatible title",
    "igdbId": 19771,
    "gbId": 4155,
    "gbGuid": "3030-4155",
    "category": "multiplayer"
  },
  {
    "name": "Yuujin no Furi Furi Girls",
    "id": "snessm109",
    "details": "SNES Super Multitap compatible title",
    "igdbId": 37751,
    "gbId": 38053,
    "gbGuid": "3030-38053",
    "category": "multiplayer"
  },
  {
    "name": "Zero 4 Champ",
    "id": "snessm110",
    "details": "SNES Super Multitap compatible title",
    "igdbId": 37648,
    "gbId": null,
    "gbGuid": null,
    "category": "multiplayer"
  },
  {
    "name": "Zero 4 Champ RR",
    "id": "snessm111",
    "details": "SNES Super Multitap compatible title",
    "igdbId": null,
    "gbId": null,
    "gbGuid": null,
    "category": "multiplayer"
  }
]