[
  {
    "name": "The 3rd Birthday",
    "details": "Sony PlayStation Portable exclusive",
    "id": "pspex1",
    "igdbId": 7359,
    "gbId": 22023,
    "gbGuid": "3030-22023",
    "tgdbId": 550
  },
  {
    "name": "300: March to Glory",
    "details": "Sony PlayStation Portable exclusive",
    "id": "pspex2",
    "igdbId": 23086,
    "gbId": 10026,
    "gbGuid": "3030-10026",
    "tgdbId": 39303
  },
  {
    "name": "Ace Combat X Skies of Deception",
    "details": "Sony PlayStation Portable exclusive",
    "id": "pspex3",
    "igdbId": 14755,
    "gbId": 9920,
    "gbGuid": "3030-9920",
    "tgdbId": 3911
  },
  {
    "name": "Ace Combat: Joint Assault",
    "details": "Sony PlayStation Portable exclusive",
    "id": "pspex4",
    "igdbId": 14757,
    "gbId": 29751,
    "gbGuid": "3030-29751",
    "tgdbId": 9303
  },
  {
    "name": "Aedis Eclipse: Generation of Chaos",
    "details": "Sony PlayStation Portable exclusive",
    "id": "pspex5",
    "igdbId": 44523,
    "gbId": 21529,
    "gbGuid": "3030-21529",
    "tgdbId": 16869
  },
  {
    "name": "AFL Challenge",
    "details": "Sony PlayStation Portable exclusive",
    "id": "pspex6",
    "igdbId": 68302,
    "gbId": 26460,
    "gbGuid": "3030-26460",
    "tgdbId": 53434
  },
  {
    "name": "After Burner: Black Falcon",
    "details": "Sony PlayStation Portable exclusive",
    "id": "pspex7",
    "igdbId": 23085,
    "gbId": 21585,
    "gbGuid": "3030-21585",
    "tgdbId": 16907
  },
  {
    "name": "Air Conflicts: Aces of World War II",
    "details": "Sony PlayStation Portable exclusive",
    "id": "pspex8",
    "igdbId": 3829,
    "gbId": 25813,
    "gbGuid": "3030-25813",
    "tgdbId": 19344
  },
  {
    "name": "Akiba's Trip",
    "details": "Sony PlayStation Portable exclusive",
    "id": "pspex9",
    "igdbId": 44279,
    "gbId": 33893,
    "gbGuid": "3030-33893",
    "tgdbId": 27853
  },
  {
    "name": "Aliens vs. Predator: Requiem",
    "details": "Sony PlayStation Portable exclusive",
    "id": "pspex10",
    "igdbId": 21675,
    "gbId": 20474,
    "gbGuid": "3030-20474",
    "tgdbId": 6461
  },
  {
    "name": "Anohana: The Flower We Saw That Day",
    "details": "Sony PlayStation Portable exclusive",
    "id": "pspex11",
    "igdbId": null,
    "gbId": null,
    "gbGuid": null,
    "tgdbId": null
  },
  {
    "name": "Another Century's Episode Portable",
    "details": "Sony PlayStation Portable exclusive",
    "id": "pspex12",
    "igdbId": 66344,
    "gbId": 32885,
    "gbGuid": "3030-32885",
    "tgdbId": null
  },
  {
    "name": "Ape Escape Academy 2",
    "details": "Sony PlayStation Portable exclusive",
    "id": "pspex13",
    "igdbId": 37047,
    "gbId": 27485,
    "gbGuid": "3030-27485",
    "tgdbId": 30528
  },
  {
    "name": "Ape Escape Academy",
    "details": "Sony PlayStation Portable exclusive",
    "id": "pspex14",
    "igdbId": 22454,
    "gbId": 15479,
    "gbGuid": "3030-15479",
    "tgdbId": 20781
  },
  {
    "name": "Ape Quest",
    "details": "Sony PlayStation Portable exclusive",
    "id": "pspex15",
    "igdbId": 42799,
    "gbId": 24206,
    "gbGuid": "3030-24206",
    "tgdbId": 20758
  },
  {
    "name": "Archer Maclean's Mercury",
    "details": "Sony PlayStation Portable exclusive",
    "id": "pspex16",
    "igdbId": 22293,
    "gbId": 6382,
    "gbGuid": "3030-6382",
    "tgdbId": 20679
  },
  {
    "name": "Assassin's Creed: Bloodlines",
    "details": "Sony PlayStation Portable exclusive",
    "id": "pspex17",
    "igdbId": 10661,
    "gbId": 25423,
    "gbGuid": "3030-25423",
    "tgdbId": 7070
  },
  {
    "name": "ATV Offroad Fury Pro",
    "details": "Sony PlayStation Portable exclusive",
    "id": "pspex18",
    "igdbId": 8274,
    "gbId": 23665,
    "gbGuid": "3030-23665",
    "tgdbId": 42238
  },
  {
    "name": "ATV Offroad Fury: Blazin' Trails",
    "details": "Sony PlayStation Portable exclusive",
    "id": "pspex19",
    "igdbId": 8272,
    "gbId": 21819,
    "gbGuid": "3030-21819",
    "tgdbId": 34345
  },
  {
    "name": "Baka and Test",
    "details": "Sony PlayStation Portable exclusive",
    "id": "pspex20",
    "igdbId": null,
    "gbId": null,
    "gbGuid": null,
    "tgdbId": null
  },
  {
    "name": "Bakumatsu Rock",
    "details": "Sony PlayStation Portable exclusive",
    "id": "pspex21",
    "igdbId": 8661,
    "gbId": 45367,
    "gbGuid": "3030-45367",
    "tgdbId": null
  },
  {
    "name": "Beats",
    "details": "Sony PlayStation Portable exclusive",
    "id": "pspex22",
    "igdbId": 79415,
    "gbId": 21831,
    "gbGuid": "3030-21831",
    "tgdbId": 61802
  },
  {
    "name": "Black Rock Shooter: The Game",
    "details": "Sony PlayStation Portable exclusive",
    "id": "pspex23",
    "igdbId": 11831,
    "gbId": 33275,
    "gbGuid": "3030-33275",
    "tgdbId": 16908
  },
  {
    "name": "Blade Dancer: Lineage of Light",
    "details": "Sony PlayStation Portable exclusive",
    "id": "pspex24",
    "igdbId": 23115,
    "gbId": 22171,
    "gbGuid": "3030-22171",
    "tgdbId": 14084
  },
  {
    "name": "Blaze Union: Story to Reach the Future",
    "details": "Sony PlayStation Portable exclusive",
    "id": "pspex25",
    "igdbId": 78107,
    "gbId": 31759,
    "gbGuid": "3030-31759",
    "tgdbId": null
  },
  {
    "name": "Bleach: Heat the Soul",
    "details": "Sony PlayStation Portable exclusive",
    "id": "pspex26",
    "igdbId": 44488,
    "gbId": 22569,
    "gbGuid": "3030-22569",
    "tgdbId": 30532
  },
  {
    "name": "Boku no Natsuyasumi 4",
    "details": "Sony PlayStation Portable exclusive",
    "id": "pspex27",
    "igdbId": 67897,
    "gbId": 27311,
    "gbGuid": "3030-27311",
    "tgdbId": null
  },
  {
    "name": "Bomberman",
    "details": "Sony PlayStation Portable exclusive",
    "id": "pspex28",
    "igdbId": null,
    "gbId": 48930,
    "gbGuid": "3030-48930",
    "tgdbId": 1040
  },
  {
    "name": "Bomberman Land",
    "details": "Sony PlayStation Portable exclusive",
    "id": "pspex29",
    "igdbId": 21613,
    "gbId": 20852,
    "gbGuid": "3030-20852",
    "tgdbId": 4194
  },
  {
    "name": "Bounty Hounds",
    "details": "Sony PlayStation Portable exclusive",
    "id": "pspex30",
    "igdbId": 38471,
    "gbId": 1995,
    "gbGuid": "3030-1995",
    "tgdbId": 31455
  },
  {
    "name": "Boxer's Road 2: The Real",
    "details": "Sony PlayStation Portable exclusive",
    "id": "pspex31",
    "igdbId": 61438,
    "gbId": 46733,
    "gbGuid": "3030-46733",
    "tgdbId": 43170
  },
  {
    "name": "Brave Story: New Traveler",
    "details": "Sony PlayStation Portable exclusive",
    "id": "pspex32",
    "igdbId": 14607,
    "gbId": 11771,
    "gbGuid": "3030-11771",
    "tgdbId": 14914
  },
  {
    "name": "Ricky Ponting 2007: Pressure Play",
    "details": "Sony PlayStation Portable exclusive",
    "id": "pspex33",
    "igdbId": 70025,
    "gbId": 15955,
    "gbGuid": "3030-15955",
    "tgdbId": 50661
  },
  {
    "name": "Brooktown High",
    "details": "Sony PlayStation Portable exclusive",
    "id": "pspex34",
    "igdbId": 19255,
    "gbId": 27780,
    "gbGuid": "3030-27780",
    "tgdbId": 50594
  },
  {
    "name": "Brothers Conflict",
    "details": "Sony PlayStation Portable exclusive",
    "id": "pspex35",
    "igdbId": null,
    "gbId": 42517,
    "gbGuid": "3030-42517",
    "tgdbId": null
  },
  {
    "name": "Brothers in Arms: D-Day",
    "details": "Sony PlayStation Portable exclusive",
    "id": "pspex36",
    "igdbId": 23117,
    "gbId": 17947,
    "gbGuid": "3030-17947",
    "tgdbId": 19347
  },
  {
    "name": "Bubble Bobble Evolution",
    "details": "Sony PlayStation Portable exclusive",
    "id": "pspex37",
    "igdbId": 38483,
    "gbId": 17865,
    "gbGuid": "3030-17865",
    "tgdbId": 27338
  },
  {
    "name": "Busou Shinki: Battle Masters Mk. 2",
    "details": "Sony PlayStation Portable exclusive",
    "id": "pspex38",
    "igdbId": 56498,
    "gbId": 58533,
    "gbGuid": "3030-58533",
    "tgdbId": 47840
  },
  {
    "name": "Buzz! Brain Bender",
    "details": "Sony PlayStation Portable exclusive",
    "id": "pspex39",
    "igdbId": 23267,
    "gbId": null,
    "gbGuid": null,
    "tgdbId": 31310
  },
  {
    "name": "Buzz! Master Quiz",
    "details": "Sony PlayStation Portable exclusive",
    "id": "pspex40",
    "igdbId": 21944,
    "gbId": 21117,
    "gbGuid": "3030-21117",
    "tgdbId": 13393
  },
  {
    "name": "Cabela's Dangerous Hunts Ultimate Challenge",
    "details": "Sony PlayStation Portable exclusive",
    "id": "pspex41",
    "igdbId": 80845,
    "gbId": 24905,
    "gbGuid": "3030-24905",
    "tgdbId": 48460
  },
  {
    "name": "Call of Duty: Roads to Victory",
    "details": "Sony PlayStation Portable exclusive",
    "id": "pspex42",
    "igdbId": 3120,
    "gbId": 7827,
    "gbGuid": "3030-7827",
    "tgdbId": 18934
  },
  {
    "name": "Capcom Puzzle World",
    "details": "Sony PlayStation Portable exclusive",
    "id": "pspex43",
    "igdbId": 44503,
    "gbId": 9046,
    "gbGuid": "3030-9046",
    "tgdbId": 24333
  },
  {
    "name": "Toaru Majutsu no Index",
    "details": "Sony PlayStation Portable exclusive",
    "id": "pspex44",
    "igdbId": 11864,
    "gbId": 45614,
    "gbGuid": "3030-45614",
    "tgdbId": 16886
  },
  {
    "name": "A Certain Scientific Railgun",
    "details": "Sony PlayStation Portable exclusive",
    "id": "pspex45",
    "igdbId": null,
    "gbId": null,
    "gbGuid": null,
    "tgdbId": null
  },
  {
    "name": "Championship Manager (PSP)",
    "details": "Sony PlayStation Portable exclusive",
    "id": "pspex46",
    "igdbId": null,
    "gbId": null,
    "gbGuid": null,
    "tgdbId": null
  },
  {
    "name": "Chili Con Carnage",
    "details": "Sony PlayStation Portable exclusive",
    "id": "pspex47",
    "igdbId": 23111,
    "gbId": 19080,
    "gbGuid": "3030-19080",
    "tgdbId": 8551
  },
  {
    "name": "Cho Aniki Zero",
    "details": "Sony PlayStation Portable exclusive",
    "id": "pspex48",
    "igdbId": 42859,
    "gbId": 29902,
    "gbGuid": "3030-29902",
    "tgdbId": 19350
  },
  {
    "name": "ClaDun: This is an RPG!",
    "details": "Sony PlayStation Portable exclusive",
    "id": "pspex49",
    "igdbId": 21576,
    "gbId": 32107,
    "gbGuid": "3030-32107",
    "tgdbId": 20551
  },
  {
    "name": "Class of Heroes",
    "details": "Sony PlayStation Portable exclusive",
    "id": "pspex50",
    "igdbId": 20998,
    "gbId": 25134,
    "gbGuid": "3030-25134",
    "tgdbId": 13046
  },
  {
    "name": "Coded Arms",
    "details": "Sony PlayStation Portable exclusive",
    "id": "pspex51",
    "igdbId": 21619,
    "gbId": 5764,
    "gbGuid": "3030-5764",
    "tgdbId": 24727
  },
  {
    "name": "Coded Arms: Contagion",
    "details": "Sony PlayStation Portable exclusive",
    "id": "pspex52",
    "igdbId": 21939,
    "gbId": 25029,
    "gbGuid": "3030-25029",
    "tgdbId": 19351
  },
  {
    "name": "Coded Soul: Uketsugareshi Idea",
    "details": "Sony PlayStation Portable exclusive",
    "id": "pspex53",
    "igdbId": 67801,
    "gbId": 27727,
    "gbGuid": "3030-27727",
    "tgdbId": 53310
  },
  {
    "name": "The Con",
    "details": "Sony PlayStation Portable exclusive",
    "id": "pspex54",
    "igdbId": 22578,
    "gbId": 20595,
    "gbGuid": "3030-20595",
    "tgdbId": 34453
  },
  {
    "name": "Crazy Taxi: Fare Wars",
    "details": "Sony PlayStation Portable exclusive",
    "id": "pspex55",
    "igdbId": 1809,
    "gbId": 9443,
    "gbGuid": "3030-9443",
    "tgdbId": 19352
  },
  {
    "name": "Crisis Core: Final Fantasy VII",
    "details": "Sony PlayStation Portable exclusive",
    "id": "pspex56",
    "igdbId": 2407,
    "gbId": 2361,
    "gbGuid": "3030-2361",
    "tgdbId": 81
  },
  {
    "name": "Daxter",
    "details": "Sony PlayStation Portable exclusive",
    "id": "pspex57",
    "igdbId": 1533,
    "gbId": 14604,
    "gbGuid": "3030-14604",
    "tgdbId": 7078
  },
  {
    "name": "Dead Head Fred",
    "details": "Sony PlayStation Portable exclusive",
    "id": "pspex58",
    "igdbId": 21047,
    "gbId": 7941,
    "gbGuid": "3030-7941",
    "tgdbId": 14903
  },
  {
    "name": "Dead to Rights: Reckoning",
    "details": "Sony PlayStation Portable exclusive",
    "id": "pspex59",
    "igdbId": 3010,
    "gbId": 9743,
    "gbGuid": "3030-9743",
    "tgdbId": 31180
  },
  {
    "name": "Death Jr.",
    "details": "Sony PlayStation Portable exclusive",
    "id": "pspex60",
    "igdbId": 45988,
    "gbId": 19740,
    "gbGuid": "3030-19740",
    "tgdbId": 19799
  },
  {
    "name": "Def Jam: Fight for NY",
    "details": "Sony PlayStation Portable exclusive",
    "id": "pspex61",
    "igdbId": 23123,
    "gbId": null,
    "gbGuid": null,
    "tgdbId": 6045
  },
  {
    "name": "Disgaea Infinite",
    "details": "Sony PlayStation Portable exclusive",
    "id": "pspex62",
    "igdbId": 21742,
    "gbId": 29233,
    "gbGuid": "3030-29233",
    "tgdbId": 16932
  },
  {
    "name": "Dissidia: Final Fantasy",
    "details": "Sony PlayStation Portable exclusive",
    "id": "pspex63",
    "igdbId": 391,
    "gbId": 21202,
    "gbGuid": "3030-21202",
    "tgdbId": 863
  },
  {
    "name": "DJ Max Fever",
    "details": "Sony PlayStation Portable exclusive",
    "id": "pspex64",
    "igdbId": 42892,
    "gbId": null,
    "gbGuid": null,
    "tgdbId": 15010
  },
  {
    "name": "DJ Max Portable",
    "details": "Sony PlayStation Portable exclusive",
    "id": "pspex65",
    "igdbId": 25913,
    "gbId": 17021,
    "gbGuid": "3030-17021",
    "tgdbId": 43136
  },
  {
    "name": "DJ Max Portable 2",
    "details": "Sony PlayStation Portable exclusive",
    "id": "pspex66",
    "igdbId": 42724,
    "gbId": 21232,
    "gbGuid": "3030-21232",
    "tgdbId": 43134
  },
  {
    "name": "DJ Max Portable 3",
    "details": "Sony PlayStation Portable exclusive",
    "id": "pspex67",
    "igdbId": 44491,
    "gbId": 31427,
    "gbGuid": "3030-31427",
    "tgdbId": 29970
  },
  {
    "name": "DJ Max Portable: Black Square",
    "details": "Sony PlayStation Portable exclusive",
    "id": "pspex68",
    "igdbId": 42745,
    "gbId": 24618,
    "gbGuid": "3030-24618",
    "tgdbId": 34501
  },
  {
    "name": "DJ Max Portable: Clazziquai Edition",
    "details": "Sony PlayStation Portable exclusive",
    "id": "pspex69",
    "igdbId": 79327,
    "gbId": 24424,
    "gbGuid": "3030-24424",
    "tgdbId": 61815
  },
  {
    "name": "DJ Max Portable Hot Tunes",
    "details": "Sony PlayStation Portable exclusive",
    "id": "pspex70",
    "igdbId": 42742,
    "gbId": 31663,
    "gbGuid": "3030-31663",
    "tgdbId": 35599
  },
  {
    "name": "Hidden Object: Dog Happy Life",
    "details": "Sony PlayStation Portable exclusive",
    "id": "pspex71",
    "igdbId": 82160,
    "gbId": 65012,
    "gbGuid": "3030-65012",
    "tgdbId": null
  },
  {
    "name": "Dragon Quest & Final Fantasy in Itadaki Street Portable",
    "details": "Sony PlayStation Portable exclusive",
    "id": "pspex72",
    "igdbId": 69176,
    "gbId": null,
    "gbGuid": null,
    "tgdbId": 19013
  },
  {
    "name": "Dragon Ball: Evolution",
    "details": "Sony PlayStation Portable exclusive",
    "id": "pspex73",
    "igdbId": 2571,
    "gbId": null,
    "gbGuid": null,
    "tgdbId": 30659
  },
  {
    "name": "Dragoneer's Aria",
    "details": "Sony PlayStation Portable exclusive",
    "id": "pspex74",
    "igdbId": 24279,
    "gbId": 21924,
    "gbGuid": "3030-21924",
    "tgdbId": 16933
  },
  {
    "name": "Driver '76",
    "details": "Sony PlayStation Portable exclusive",
    "id": "pspex75",
    "igdbId": 22018,
    "gbId": 4486,
    "gbGuid": "3030-4486",
    "tgdbId": 19355
  },
  {
    "name": "Dungeon Maker: Hunting Ground",
    "details": "Sony PlayStation Portable exclusive",
    "id": "pspex76",
    "igdbId": 24284,
    "gbId": 14484,
    "gbGuid": "3030-14484",
    "tgdbId": 24795
  },
  {
    "name": "Dungeon Siege: Throne of Agony",
    "details": "Sony PlayStation Portable exclusive",
    "id": "pspex77",
    "igdbId": 9270,
    "gbId": 11620,
    "gbGuid": "3030-11620",
    "tgdbId": 24334
  },
  {
    "name": "Dungeons & Dragons Tactics",
    "details": "Sony PlayStation Portable exclusive",
    "id": "pspex78",
    "igdbId": 23051,
    "gbId": 21996,
    "gbGuid": "3030-21996",
    "tgdbId": 16912
  },
  {
    "name": "Dynasty Warriors",
    "details": "Sony PlayStation Portable exclusive",
    "id": "pspex79",
    "igdbId": 2982,
    "gbId": 21743,
    "gbGuid": "3030-21743",
    "tgdbId": 14216
  },
  {
    "name": "Dynasty Warriors Vol. 2",
    "details": "Sony PlayStation Portable exclusive",
    "id": "pspex80",
    "igdbId": 42886,
    "gbId": 21764,
    "gbGuid": "3030-21764",
    "tgdbId": 13939
  },
  {
    "name": "EA Replay",
    "details": "Sony PlayStation Portable exclusive",
    "id": "pspex81",
    "igdbId": 23084,
    "gbId": 10965,
    "gbGuid": "3030-10965",
    "tgdbId": 18190
  },
  {
    "name": "Echoshift",
    "details": "Sony PlayStation Portable exclusive",
    "id": "pspex82",
    "igdbId": 22976,
    "gbId": 26908,
    "gbGuid": "3030-26908",
    "tgdbId": 20000
  },
  {
    "name": "Elminage",
    "details": "Sony PlayStation Portable exclusive",
    "id": "pspex83",
    "igdbId": null,
    "gbId": null,
    "gbGuid": null,
    "tgdbId": null
  },
  {
    "name": "Everybody's Golf Portable",
    "details": "Sony PlayStation Portable exclusive",
    "id": "pspex84",
    "igdbId": 22453,
    "gbId": null,
    "gbGuid": null,
    "tgdbId": null
  },
  {
    "name": "Everybody's Golf Portable 2",
    "details": "Sony PlayStation Portable exclusive",
    "id": "pspex85",
    "igdbId": 21050,
    "gbId": null,
    "gbGuid": null,
    "tgdbId": null
  },
  {
    "name": "Everybody's Tennis Portable",
    "details": "Sony PlayStation Portable exclusive",
    "id": "pspex86",
    "igdbId": 21754,
    "gbId": null,
    "gbGuid": null,
    "tgdbId": null
  },
  {
    "name": "The Eye of Judgment: Legends",
    "details": "Sony PlayStation Portable exclusive",
    "id": "pspex87",
    "igdbId": 46020,
    "gbId": 30555,
    "gbGuid": "3030-30555",
    "tgdbId": 35872
  },
  {
    "name": "F1 Grand Prix",
    "details": "Sony PlayStation Portable exclusive",
    "id": "pspex88",
    "igdbId": 38472,
    "gbId": 15352,
    "gbGuid": "3030-15352",
    "tgdbId": 31319
  },
  {
    "name": "Fate/Extra",
    "details": "Sony PlayStation Portable exclusive",
    "id": "pspex89",
    "igdbId": 12382,
    "gbId": 30825,
    "gbGuid": "3030-30825",
    "tgdbId": 16709
  },
  {
    "name": "Fate/Tiger Colosseum",
    "details": "Sony PlayStation Portable exclusive",
    "id": "pspex90",
    "igdbId": 12331,
    "gbId": 22027,
    "gbGuid": "3030-22027",
    "tgdbId": 23921
  },
  {
    "name": "Field Commander",
    "details": "Sony PlayStation Portable exclusive",
    "id": "pspex91",
    "igdbId": 42873,
    "gbId": 4563,
    "gbGuid": "3030-4563",
    "tgdbId": 7081
  },
  {
    "name": "Final Fantasy IV: The Complete Collection",
    "details": "Sony PlayStation Portable exclusive",
    "id": "pspex92",
    "igdbId": 21779,
    "gbId": 34076,
    "gbGuid": "3030-34076",
    "tgdbId": 3735
  },
  {
    "name": "Final Fantasy Type-0",
    "details": "Sony PlayStation Portable exclusive",
    "id": "pspex93",
    "igdbId": 383,
    "gbId": 21848,
    "gbGuid": "3030-21848",
    "tgdbId": 21002
  },
  {
    "name": "Finder Love",
    "details": "Sony PlayStation Portable exclusive",
    "id": "pspex94",
    "igdbId": null,
    "gbId": null,
    "gbGuid": null,
    "tgdbId": null
  },
  {
    "name": "Fired Up",
    "details": "Sony PlayStation Portable exclusive",
    "id": "pspex95",
    "igdbId": 22451,
    "gbId": 21166,
    "gbGuid": "3030-21166",
    "tgdbId": 19361
  },
  {
    "name": "Frantix: A Puzzle Adventure",
    "details": "Sony PlayStation Portable exclusive",
    "id": "pspex96",
    "igdbId": 22563,
    "gbId": 3881,
    "gbGuid": "3030-3881",
    "tgdbId": 40267
  },
  {
    "name": "Gangs Of London",
    "details": "Sony PlayStation Portable exclusive",
    "id": "pspex97",
    "igdbId": 23136,
    "gbId": 20591,
    "gbGuid": "3030-20591",
    "tgdbId": 19365
  },
  {
    "name": "Generation of Chaos: Pandora's Reflection",
    "details": "Sony PlayStation Portable exclusive",
    "id": "pspex98",
    "igdbId": 21018,
    "gbId": 40252,
    "gbGuid": "3030-40252",
    "tgdbId": 16913
  },
  {
    "name": "Genso Suikoden I & II",
    "details": "Sony PlayStation Portable exclusive",
    "id": "pspex99",
    "igdbId": null,
    "gbId": null,
    "gbGuid": null,
    "tgdbId": null
  },
  {
    "name": "Genso Suikoden: Tsumugareshi Hyakunen no Toki",
    "details": "Sony PlayStation Portable exclusive",
    "id": "pspex100",
    "igdbId": 1453,
    "gbId": 36942,
    "gbGuid": "3030-36942",
    "tgdbId": 51976
  },
  {
    "name": "Ghost in the Shell: Stand Alone Complex",
    "details": "Sony PlayStation Portable exclusive",
    "id": "pspex101",
    "igdbId": 114138,
    "gbId": 22944,
    "gbGuid": "3030-22944",
    "tgdbId": 5385
  },
  {
    "name": "Tom Clancy's Ghost Recon Predator",
    "details": "Sony PlayStation Portable exclusive",
    "id": "pspex102",
    "igdbId": 1302,
    "gbId": null,
    "gbGuid": null,
    "tgdbId": 27576
  },
  {
    "name": "Gladiator Begins",
    "details": "Sony PlayStation Portable exclusive",
    "id": "pspex103",
    "igdbId": 41028,
    "gbId": 27744,
    "gbGuid": "3030-27744",
    "tgdbId": 19375
  },
  {
    "name": "Gloria Union: Twin Fates in Blue Ocean",
    "details": "Sony PlayStation Portable exclusive",
    "id": "pspex104",
    "igdbId": 66057,
    "gbId": 34627,
    "gbGuid": "3030-34627",
    "tgdbId": null
  },
  {
    "name": "Gran Turismo",
    "details": "Sony PlayStation Portable exclusive",
    "id": "pspex105",
    "igdbId": 20426,
    "gbId": 26842,
    "gbGuid": "3030-26842",
    "tgdbId": 5632
  },
  {
    "name": "Grand Knights History",
    "details": "Sony PlayStation Portable exclusive",
    "id": "pspex106",
    "igdbId": 42808,
    "gbId": 34617,
    "gbGuid": "3030-34617",
    "tgdbId": 23259
  },
  {
    "name": "Great Battle Full Blast",
    "details": "Sony PlayStation Portable exclusive",
    "id": "pspex107",
    "igdbId": 65516,
    "gbId": 36911,
    "gbGuid": "3030-36911",
    "tgdbId": null
  },
  {
    "name": "Guilty Gear: Judgement",
    "details": "Sony PlayStation Portable exclusive",
    "id": "pspex108",
    "igdbId": 24196,
    "gbId": 21802,
    "gbGuid": "3030-21802",
    "tgdbId": 7087
  },
  {
    "name": "Gundam Battle Chronicle",
    "details": "Sony PlayStation Portable exclusive",
    "id": "pspex109",
    "igdbId": 66596,
    "gbId": 31310,
    "gbGuid": "3030-31310",
    "tgdbId": null
  },
  {
    "name": "Gundam Battle Royale",
    "details": "Sony PlayStation Portable exclusive",
    "id": "pspex275",
    "igdbId": 72879,
    "gbId": 22614,
    "gbGuid": "3030-22614",
    "tgdbId": 62735
  },
  {
    "name": "Gundam Battle Tactics",
    "details": "Sony PlayStation Portable exclusive",
    "id": "pspex276",
    "igdbId": 42717,
    "gbId": 22606,
    "gbGuid": "3030-22606",
    "tgdbId": 44246
  },
  {
    "name": "Gundam Battle Universe",
    "details": "Sony PlayStation Portable exclusive",
    "id": "pspex277",
    "igdbId": 72752,
    "gbId": 23091,
    "gbGuid": "3030-23091",
    "tgdbId": 50791
  },
  {
    "name": "Gungnir",
    "details": "Sony PlayStation Portable exclusive",
    "id": "pspex110",
    "igdbId": 42882,
    "gbId": 34264,
    "gbGuid": "3030-34264",
    "tgdbId": 13321
  },
  {
    "name": ".hack//Link",
    "details": "Sony PlayStation Portable exclusive",
    "id": "pspex111",
    "igdbId": 69401,
    "gbId": 25133,
    "gbGuid": "3030-25133",
    "tgdbId": 61059
  },
  {
    "name": "Haganai",
    "details": "Sony PlayStation Portable exclusive",
    "id": "pspex112",
    "igdbId": null,
    "gbId": null,
    "gbGuid": null,
    "tgdbId": null
  },
  {
    "name": "Hammerin' Hero",
    "details": "Sony PlayStation Portable exclusive",
    "id": "pspex113",
    "igdbId": 42842,
    "gbId": 24864,
    "gbGuid": "3030-24864",
    "tgdbId": 19435
  },
  {
    "name": "Harvest Moon: Hero of Leaf Valley",
    "details": "Sony PlayStation Portable exclusive",
    "id": "pspex114",
    "igdbId": 42887,
    "gbId": 30915,
    "gbGuid": "3030-30915",
    "tgdbId": 14489
  },
  {
    "name": "Heaven's Lost Property",
    "details": "Sony PlayStation Portable exclusive",
    "id": "pspex115",
    "igdbId": null,
    "gbId": null,
    "gbGuid": null,
    "tgdbId": null
  },
  {
    "name": "Heroes Phantasia",
    "details": "Sony PlayStation Portable exclusive",
    "id": "pspex116",
    "igdbId": 65495,
    "gbId": 37015,
    "gbGuid": "3030-37015",
    "tgdbId": null
  },
  {
    "name": "Hexyz Force",
    "details": "Sony PlayStation Portable exclusive",
    "id": "pspex117",
    "igdbId": 42884,
    "gbId": 27501,
    "gbGuid": "3030-27501",
    "tgdbId": 13654
  },
  {
    "name": "Higanjima",
    "details": "Sony PlayStation Portable exclusive",
    "id": "pspex118",
    "igdbId": 94205,
    "gbId": 37352,
    "gbGuid": "3030-37352",
    "tgdbId": null
  },
  {
    "name": "Hot Pixel",
    "details": "Sony PlayStation Portable exclusive",
    "id": "pspex119",
    "igdbId": 23096,
    "gbId": 8776,
    "gbGuid": "3030-8776",
    "tgdbId": 20066
  },
  {
    "name": "Hot Wheels: Ultimate Racing",
    "details": "Sony PlayStation Portable exclusive",
    "id": "pspex120",
    "igdbId": 44482,
    "gbId": 15349,
    "gbGuid": "3030-15349",
    "tgdbId": 30539
  },
  {
    "name": "The Idolm@ster SP: Perfect Sun",
    "details": "Sony PlayStation Portable exclusive",
    "id": "pspex121",
    "igdbId": 38441,
    "gbId": 58152,
    "gbGuid": "3030-58152",
    "tgdbId": 38677
  },
  {
    "name": "The Idolm@ster SP: Wandering Star",
    "details": "Sony PlayStation Portable exclusive",
    "id": "pspex278",
    "igdbId": 38439,
    "gbId": 58153,
    "gbGuid": "3030-58153",
    "tgdbId": 38680
  },
  {
    "name": "The Idolm@ster SP: Missing Moon",
    "details": "Sony PlayStation Portable exclusive",
    "id": "pspex279",
    "igdbId": 38440,
    "gbId": 58151,
    "gbGuid": "3030-58151",
    "tgdbId": 38678
  },
  {
    "name": "Infected",
    "details": "Sony PlayStation Portable exclusive",
    "id": "pspex122",
    "igdbId": 44524,
    "gbId": 2988,
    "gbGuid": "3030-2988",
    "tgdbId": 16916
  },
  {
    "name": "InviZimals",
    "details": "Sony PlayStation Portable exclusive",
    "id": "pspex123",
    "igdbId": 2994,
    "gbId": 26906,
    "gbGuid": "3030-26906",
    "tgdbId": 17882
  },
  {
    "name": "Invizimals: Shadow Zone",
    "details": "Sony PlayStation Portable exclusive",
    "id": "pspex124",
    "igdbId": 2996,
    "gbId": 35803,
    "gbGuid": "3030-35803",
    "tgdbId": 30612
  },
  {
    "name": "Invizimals: The Lost Tribes",
    "details": "Sony PlayStation Portable exclusive",
    "id": "pspex125",
    "igdbId": 3001,
    "gbId": 35804,
    "gbGuid": "3030-35804",
    "tgdbId": 27573
  },
  {
    "name": "Jeanne d'Arc",
    "details": "Sony PlayStation Portable exclusive",
    "id": "pspex126",
    "igdbId": 11326,
    "gbId": 20593,
    "gbGuid": "3030-20593",
    "tgdbId": 7088
  },
  {
    "name": "Jikandia: The Timeless Land",
    "details": "Sony PlayStation Portable exclusive",
    "id": "pspex127",
    "igdbId": 17268,
    "gbId": 31372,
    "gbGuid": "3030-31372",
    "tgdbId": 13826
  },
  {
    "name": "Juiced: Eliminator",
    "details": "Sony PlayStation Portable exclusive",
    "id": "pspex128",
    "igdbId": 18262,
    "gbId": 21310,
    "gbGuid": "3030-21310",
    "tgdbId": 29869
  },
  {
    "name": "Kamigami no Asobi",
    "details": "Sony PlayStation Portable exclusive",
    "id": "pspex129",
    "igdbId": null,
    "gbId": null,
    "gbGuid": null,
    "tgdbId": null
  },
  {
    "name": "Kao Challengers",
    "details": "Sony PlayStation Portable exclusive",
    "id": "pspex130",
    "igdbId": 22564,
    "gbId": 19548,
    "gbGuid": "3030-19548",
    "tgdbId": 14478
  },
  {
    "name": "Kenka Bancho: Badass Rumble",
    "details": "Sony PlayStation Portable exclusive",
    "id": "pspex131",
    "igdbId": 21891,
    "gbId": 27256,
    "gbGuid": "3030-27256",
    "tgdbId": 19521
  },
  {
    "name": "Killzone: Liberation",
    "details": "Sony PlayStation Portable exclusive",
    "id": "pspex132",
    "igdbId": 1868,
    "gbId": 5556,
    "gbGuid": "3030-5556",
    "tgdbId": 15156
  },
  {
    "name": "Kingdom of Paradise",
    "details": "Sony PlayStation Portable exclusive",
    "id": "pspex133",
    "igdbId": 42878,
    "gbId": 7048,
    "gbGuid": "3030-7048",
    "tgdbId": 13392
  },
  {
    "name": "Kokoro Connect Yochi Random",
    "details": "Sony PlayStation Portable exclusive",
    "id": "pspex134",
    "igdbId": 112296,
    "gbId": 70539,
    "gbGuid": "3030-70539",
    "tgdbId": null
  },
  {
    "name": "Kurohyou: Ryu ga Gotoku Shinshou",
    "details": "Sony PlayStation Portable exclusive",
    "id": "pspex135",
    "igdbId": 66611,
    "gbId": 31243,
    "gbGuid": "3030-31243",
    "tgdbId": 33263
  },
  {
    "name": "La Storia della Arcana Famiglia",
    "details": "Sony PlayStation Portable exclusive",
    "id": "pspex136",
    "igdbId": 81580,
    "gbId": 39553,
    "gbGuid": "3030-39553",
    "tgdbId": null
  },
  {
    "name": "Last Ranker",
    "details": "Sony PlayStation Portable exclusive",
    "id": "pspex137",
    "igdbId": 38461,
    "gbId": 28131,
    "gbGuid": "3030-28131",
    "tgdbId": 31612
  },
  {
    "name": "LittleBigPlanet",
    "details": "Sony PlayStation Portable exclusive",
    "id": "pspex138",
    "igdbId": 1058,
    "gbId": 25422,
    "gbGuid": "3030-25422",
    "tgdbId": 809
  },
  {
    "name": "LocoRoco",
    "details": "Sony PlayStation Portable exclusive",
    "id": "pspex139",
    "igdbId": 1459,
    "gbId": 9410,
    "gbGuid": "3030-9410",
    "tgdbId": 7094
  },
  {
    "name": "LocoRoco 2",
    "details": "Sony PlayStation Portable exclusive",
    "id": "pspex140",
    "igdbId": 1461,
    "gbId": 21111,
    "gbGuid": "3030-21111",
    "tgdbId": 14546
  },
  {
    "name": "LocoRoco Midnight Carnival",
    "details": "Sony PlayStation Portable exclusive",
    "id": "pspex141",
    "igdbId": 1462,
    "gbId": 27865,
    "gbGuid": "3030-27865",
    "tgdbId": null
  },
  {
    "name": "Lord of Arcana",
    "details": "Sony PlayStation Portable exclusive",
    "id": "pspex142",
    "igdbId": 21736,
    "gbId": 32630,
    "gbGuid": "3030-32630",
    "tgdbId": 20760
  },
  {
    "name": "The Lord of the Rings: Tactics",
    "details": "Sony PlayStation Portable exclusive",
    "id": "pspex143",
    "igdbId": 22458,
    "gbId": 5219,
    "gbGuid": "3030-5219",
    "tgdbId": 14484
  },
  {
    "name": "Lumines II",
    "details": "Sony PlayStation Portable exclusive",
    "id": "pspex144",
    "igdbId": 4690,
    "gbId": 1601,
    "gbGuid": "3030-1601",
    "tgdbId": 16917
  },
  {
    "name": "Lunar: Silver Star Harmony",
    "details": "Sony PlayStation Portable exclusive",
    "id": "pspex145",
    "igdbId": 13909,
    "gbId": 26422,
    "gbGuid": "3030-26422",
    "tgdbId": 7096
  },
  {
    "name": "Macross Ace Frontier",
    "details": "Sony PlayStation Portable exclusive",
    "id": "pspex146",
    "igdbId": 44486,
    "gbId": 22918,
    "gbGuid": "3030-22918",
    "tgdbId": 28934
  },
  {
    "name": "Mahou Shoujo Lyrical Nanoha A's Portable: The Battle of Aces",
    "details": "Sony PlayStation Portable exclusive",
    "id": "pspex147",
    "igdbId": 42836,
    "gbId": 38886,
    "gbGuid": "3030-38886",
    "tgdbId": 19512
  },
  {
    "name": "Mahou Shoujo Nanoha A's Portable: The Gears of Destiny",
    "details": "Sony PlayStation Portable exclusive",
    "id": "pspex280",
    "igdbId": 38451,
    "gbId": 38887,
    "gbGuid": "3030-38887",
    "tgdbId": 35713
  },
  {
    "name": "Marriage Royale",
    "details": "Sony PlayStation Portable exclusive",
    "id": "pspex148",
    "igdbId": null,
    "gbId": null,
    "gbGuid": null,
    "tgdbId": null
  },
  {
    "name": "Me & My Katamari",
    "details": "Sony PlayStation Portable exclusive",
    "id": "pspex149",
    "igdbId": 6455,
    "gbId": 6924,
    "gbGuid": "3030-6924",
    "tgdbId": 12533
  },
  {
    "name": "Medal of Honor: Heroes",
    "details": "Sony PlayStation Portable exclusive",
    "id": "pspex150",
    "igdbId": 1312,
    "gbId": 5484,
    "gbGuid": "3030-5484",
    "tgdbId": 7098
  },
  {
    "name": "MediEvil: Resurrection",
    "details": "Sony PlayStation Portable exclusive",
    "id": "pspex151",
    "igdbId": 4005,
    "gbId": 14258,
    "gbGuid": "3030-14258",
    "tgdbId": 7099
  },
  {
    "name": "Mega Man Powered Up",
    "details": "Sony PlayStation Portable exclusive",
    "id": "pspex152",
    "igdbId": 12937,
    "gbId": 16360,
    "gbGuid": "3030-16360",
    "tgdbId": 7100
  },
  {
    "name": "Metal Gear Acid",
    "details": "Sony PlayStation Portable exclusive",
    "id": "pspex153",
    "igdbId": 12211,
    "gbId": 9600,
    "gbGuid": "3030-9600",
    "tgdbId": 43
  },
  {
    "name": "Metal Gear Acid 2",
    "details": "Sony PlayStation Portable exclusive",
    "id": "pspex154",
    "igdbId": 9886,
    "gbId": null,
    "gbGuid": null,
    "tgdbId": 7102
  },
  {
    "name": "Miami Vice",
    "details": "Sony PlayStation Portable exclusive",
    "id": "pspex155",
    "igdbId": 23818,
    "gbId": 1440,
    "gbGuid": "3030-1440",
    "tgdbId": 30540
  },
  {
    "name": "Midway Arcade Treasures: Extended Play",
    "details": "Sony PlayStation Portable exclusive",
    "id": "pspex156",
    "igdbId": 71407,
    "gbId": 3538,
    "gbGuid": "3030-3538",
    "tgdbId": 29063
  },
  {
    "name": "Mimana Iyar Chronicle",
    "details": "Sony PlayStation Portable exclusive",
    "id": "pspex157",
    "igdbId": 42711,
    "gbId": 29104,
    "gbGuid": "3030-29104",
    "tgdbId": 14046
  },
  {
    "name": "Misshitsu no Sacrifice",
    "details": "Sony PlayStation Portable exclusive",
    "id": "pspex158",
    "igdbId": 78401,
    "gbId": 29700,
    "gbGuid": "3030-29700",
    "tgdbId": null
  },
  {
    "name": "Mobile Suit Gundam AGE: Cosmic Drive",
    "details": "Sony PlayStation Portable exclusive",
    "id": "pspex159",
    "igdbId": 75722,
    "gbId": 36645,
    "gbGuid": "3030-36645",
    "tgdbId": null
  },
  {
    "name": "Monogatari (series)",
    "details": "Sony PlayStation Portable exclusive",
    "id": "pspex160",
    "igdbId": null,
    "gbId": null,
    "gbGuid": null,
    "tgdbId": null
  },
  {
    "name": "Monster Hunter Freedom",
    "details": "Sony PlayStation Portable exclusive",
    "id": "pspex161",
    "igdbId": 2269,
    "gbId": 13822,
    "gbGuid": "3030-13822",
    "tgdbId": 7105
  },
  {
    "name": "Monster Hunter Freedom 2",
    "details": "Sony PlayStation Portable exclusive",
    "id": "pspex162",
    "igdbId": 23066,
    "gbId": 20223,
    "gbGuid": "3030-20223",
    "tgdbId": 20078
  },
  {
    "name": "Monster Kingdom: Jewel Summoner",
    "details": "Sony PlayStation Portable exclusive",
    "id": "pspex163",
    "igdbId": 42890,
    "gbId": 3364,
    "gbGuid": "3030-3364",
    "tgdbId": 14003
  },
  {
    "name": "MotoGP",
    "details": "Sony PlayStation Portable exclusive",
    "id": "pspex164",
    "igdbId": 23012,
    "gbId": 7808,
    "gbGuid": "3030-7808",
    "tgdbId": 19373
  },
  {
    "name": "Musou Tourou",
    "details": "Sony PlayStation Portable exclusive",
    "id": "pspex165",
    "igdbId": null,
    "gbId": 51927,
    "gbGuid": "3030-51927",
    "tgdbId": null
  },
  {
    "name": "MX vs. ATV: On the Edge",
    "details": "Sony PlayStation Portable exclusive",
    "id": "pspex166",
    "igdbId": 18267,
    "gbId": 5389,
    "gbGuid": "3030-5389",
    "tgdbId": null
  },
  {
    "name": "Mytran Wars",
    "details": "Sony PlayStation Portable exclusive",
    "id": "pspex167",
    "igdbId": 19202,
    "gbId": 24597,
    "gbGuid": "3030-24597",
    "tgdbId": 44149
  },
  {
    "name": "Namco Museum Battle Collection",
    "details": "Sony PlayStation Portable exclusive",
    "id": "pspex168",
    "igdbId": 46000,
    "gbId": null,
    "gbGuid": null,
    "tgdbId": 31176
  },
  {
    "name": "Nayuta no Kiseki",
    "details": "Sony PlayStation Portable exclusive",
    "id": "pspex169",
    "igdbId": 42722,
    "gbId": 37980,
    "gbGuid": "3030-37980",
    "tgdbId": 44436
  },
  {
    "name": "NBA",
    "details": "Sony PlayStation Portable exclusive",
    "id": "pspex170",
    "igdbId": null,
    "gbId": 22315,
    "gbGuid": "3030-22315",
    "tgdbId": 48320
  },
  {
    "name": "NBA Ballers Rebound",
    "details": "Sony PlayStation Portable exclusive",
    "id": "pspex171",
    "igdbId": 72721,
    "gbId": 23316,
    "gbGuid": "3030-23316",
    "tgdbId": 48523
  },
  {
    "name": "NBA Street Showdown",
    "details": "Sony PlayStation Portable exclusive",
    "id": "pspex172",
    "igdbId": 38479,
    "gbId": 698,
    "gbGuid": "3030-698",
    "tgdbId": 33330
  },
  {
    "name": "NeoGeo Heroes: Ultimate Shooting",
    "details": "Sony PlayStation Portable exclusive",
    "id": "pspex173",
    "igdbId": 44507,
    "gbId": 31237,
    "gbGuid": "3030-31237",
    "tgdbId": 19382
  },
  {
    "name": "Neopets Petpet Adventures: The Wand of Wishing",
    "details": "Sony PlayStation Portable exclusive",
    "id": "pspex174",
    "igdbId": null,
    "gbId": 24968,
    "gbGuid": "3030-24968",
    "tgdbId": 50595
  },
  {
    "name": "Nichijou: Uchuujin",
    "details": "Sony PlayStation Portable exclusive",
    "id": "pspex175",
    "igdbId": 63077,
    "gbId": 43392,
    "gbGuid": "3030-43392",
    "tgdbId": 47695
  },
  {
    "name": "Nogizaka Haruka no Himitsu",
    "details": "Sony PlayStation Portable exclusive",
    "id": "pspex176",
    "igdbId": null,
    "gbId": null,
    "gbGuid": null,
    "tgdbId": null
  },
  {
    "name": "Ōkami Kakushi",
    "details": "Sony PlayStation Portable exclusive",
    "id": "pspex177",
    "igdbId": null,
    "gbId": null,
    "gbGuid": null,
    "tgdbId": null
  },
  {
    "name": "Online Chess Kingdoms",
    "details": "Sony PlayStation Portable exclusive",
    "id": "pspex178",
    "igdbId": 93388,
    "gbId": 4342,
    "gbGuid": "3030-4342",
    "tgdbId": 53178
  },
  {
    "name": "Patapon",
    "details": "Sony PlayStation Portable exclusive",
    "id": "pspex179",
    "igdbId": 7812,
    "gbId": 14147,
    "gbGuid": "3030-14147",
    "tgdbId": 5969
  },
  {
    "name": "Patapon 2",
    "details": "Sony PlayStation Portable exclusive",
    "id": "pspex180",
    "igdbId": 7813,
    "gbId": 21113,
    "gbGuid": "3030-21113",
    "tgdbId": 12083
  },
  {
    "name": "Patapon 3",
    "details": "Sony PlayStation Portable exclusive",
    "id": "pspex182",
    "igdbId": 18373,
    "gbId": 31751,
    "gbGuid": "3030-31751",
    "tgdbId": 12084
  },
  {
    "name": "Phantasy Star Portable",
    "details": "Sony PlayStation Portable exclusive",
    "id": "pspex183",
    "igdbId": 21873,
    "gbId": 20887,
    "gbGuid": "3030-20887",
    "tgdbId": 13789
  },
  {
    "name": "Phantasy Star Portable 2",
    "details": "Sony PlayStation Portable exclusive",
    "id": "pspex184",
    "igdbId": 19256,
    "gbId": 27657,
    "gbGuid": "3030-27657",
    "tgdbId": 15055
  },
  {
    "name": "Pilot Academy",
    "details": "Sony PlayStation Portable exclusive",
    "id": "pspex185",
    "igdbId": 23121,
    "gbId": 25329,
    "gbGuid": "3030-25329",
    "tgdbId": 19385
  },
  {
    "name": "Planet PSP",
    "details": "Sony PlayStation Portable exclusive",
    "id": "pspex186",
    "igdbId": null,
    "gbId": null,
    "gbGuid": null,
    "tgdbId": null
  },
  {
    "name": "Pocket Pool",
    "details": "Sony PlayStation Portable exclusive",
    "id": "pspex187",
    "igdbId": 21618,
    "gbId": 20565,
    "gbGuid": "3030-20565",
    "tgdbId": 20084
  },
  {
    "name": "Portable Island: Te no Hira no Resort",
    "details": "Sony PlayStation Portable exclusive",
    "id": "pspex188",
    "igdbId": null,
    "gbId": null,
    "gbGuid": null,
    "tgdbId": null
  },
  {
    "name": "PQ: Practical Intelligence Quotient",
    "details": "Sony PlayStation Portable exclusive",
    "id": "pspex189",
    "igdbId": 46019,
    "gbId": 10673,
    "gbGuid": "3030-10673",
    "tgdbId": 12279
  },
  {
    "name": "PQ2: Practical Intelligence Quotient",
    "details": "Sony PlayStation Portable exclusive",
    "id": "pspex190",
    "igdbId": 44506,
    "gbId": 20566,
    "gbGuid": "3030-20566",
    "tgdbId": 19388
  },
  {
    "name": "Prinny 2: Dawn of Operation Panties Dood!",
    "details": "Sony PlayStation Portable exclusive",
    "id": "pspex191",
    "igdbId": 21769,
    "gbId": 29106,
    "gbGuid": "3030-29106",
    "tgdbId": 62602
  },
  {
    "name": "Prinny Can I Really Be the Hero?",
    "details": "Sony PlayStation Portable exclusive",
    "id": "pspex192",
    "igdbId": 19101,
    "gbId": 23692,
    "gbGuid": "3030-23692",
    "tgdbId": 14059
  },
  {
    "name": "Puella Magi Madoka Magica Portable",
    "details": "Sony PlayStation Portable exclusive",
    "id": "pspex193",
    "igdbId": 11846,
    "gbId": 38890,
    "gbGuid": "3030-38890",
    "tgdbId": 31935
  },
  {
    "name": "Pursuit Force",
    "details": "Sony PlayStation Portable exclusive",
    "id": "pspex194",
    "igdbId": 26995,
    "gbId": 205,
    "gbGuid": "3030-205",
    "tgdbId": 19391
  },
  {
    "name": "Pursuit Force: Extreme Justice",
    "details": "Sony PlayStation Portable exclusive",
    "id": "pspex195",
    "igdbId": 23055,
    "gbId": 22289,
    "gbGuid": "3030-22289",
    "tgdbId": 19392
  },
  {
    "name": "Puzzle Guzzle",
    "details": "Sony PlayStation Portable exclusive",
    "id": "pspex196",
    "igdbId": 78105,
    "gbId": 20997,
    "gbGuid": "3030-20997",
    "tgdbId": 50596
  },
  {
    "name": "Queen's Gate: Spiral Chaos",
    "details": "Sony PlayStation Portable exclusive",
    "id": "pspex197",
    "igdbId": 66176,
    "gbId": 33585,
    "gbGuid": "3030-33585",
    "tgdbId": null
  },
  {
    "name": "R-15 (novel series)",
    "details": "Sony PlayStation Portable exclusive",
    "id": "pspex198",
    "igdbId": null,
    "gbId": null,
    "gbGuid": null,
    "tgdbId": null
  },
  {
    "name": "R-Type Tactics",
    "details": "Sony PlayStation Portable exclusive",
    "id": "pspex199",
    "igdbId": 23036,
    "gbId": null,
    "gbGuid": null,
    "tgdbId": 37132
  },
  {
    "name": "R-Type Tactics II: Operation Bitter Chocolate",
    "details": "Sony PlayStation Portable exclusive",
    "id": "pspex200",
    "igdbId": 44505,
    "gbId": 27742,
    "gbGuid": "3030-27742",
    "tgdbId": 19393
  },
  {
    "name": "Race Driver 2006",
    "details": "Sony PlayStation Portable exclusive",
    "id": "pspex201",
    "igdbId": 93991,
    "gbId": 23808,
    "gbGuid": "3030-23808",
    "tgdbId": null
  },
  {
    "name": "Ragnarok Tactics",
    "details": "Sony PlayStation Portable exclusive",
    "id": "pspex202",
    "igdbId": 21702,
    "gbId": 39125,
    "gbGuid": "3030-39125",
    "tgdbId": 14259
  },
  {
    "name": "Rainbow Islands Evolution",
    "details": "Sony PlayStation Portable exclusive",
    "id": "pspex203",
    "igdbId": 23087,
    "gbId": 29072,
    "gbGuid": "3030-29072",
    "tgdbId": 14479
  },
  {
    "name": "Rengoku II: The Stairway to H.E.A.V.E.N.",
    "details": "Sony PlayStation Portable exclusive",
    "id": "pspex204",
    "igdbId": 24185,
    "gbId": 17183,
    "gbGuid": "3030-17183",
    "tgdbId": 31213
  },
  {
    "name": "Resistance: Retribution",
    "details": "Sony PlayStation Portable exclusive",
    "id": "pspex205",
    "igdbId": 22885,
    "gbId": 21109,
    "gbGuid": "3030-21109",
    "tgdbId": 17662
  },
  {
    "name": "Ridge Racer",
    "details": "Sony PlayStation Portable exclusive",
    "id": "pspex206",
    "igdbId": 18787,
    "gbId": 23114,
    "gbGuid": "3030-23114",
    "tgdbId": 7112
  },
  {
    "name": "Ridge Racer 2",
    "details": "Sony PlayStation Portable exclusive",
    "id": "pspex207",
    "igdbId": 76259,
    "gbId": 23116,
    "gbGuid": "3030-23116",
    "tgdbId": 19394
  },
  {
    "name": "Rock Band Unplugged",
    "details": "Sony PlayStation Portable exclusive",
    "id": "pspex208",
    "igdbId": 2721,
    "gbId": 25421,
    "gbGuid": "3030-25421",
    "tgdbId": 24343
  },
  {
    "name": "Rocky Balboa",
    "details": "Sony PlayStation Portable exclusive",
    "id": "pspex209",
    "igdbId": 23112,
    "gbId": 37028,
    "gbGuid": "3030-37028",
    "tgdbId": 19395
  },
  {
    "name": "Rugby League Challenge",
    "details": "Sony PlayStation Portable exclusive",
    "id": "pspex210",
    "igdbId": 77134,
    "gbId": 28874,
    "gbGuid": "3030-28874",
    "tgdbId": null
  },
  {
    "name": "Saru! Get You!",
    "details": "Sony PlayStation Portable exclusive",
    "id": "pspex211",
    "igdbId": 79069,
    "gbId": 52247,
    "gbGuid": "3030-52247",
    "tgdbId": 25620
  },
  {
    "name": "Shining Ark",
    "details": "Sony PlayStation Portable exclusive",
    "id": "pspex212",
    "igdbId": 64460,
    "gbId": 40112,
    "gbGuid": "3030-40112",
    "tgdbId": null
  },
  {
    "name": "Shining Blade",
    "details": "Sony PlayStation Portable exclusive",
    "id": "pspex213",
    "igdbId": 65348,
    "gbId": 37724,
    "gbGuid": "3030-37724",
    "tgdbId": 47965
  },
  {
    "name": "Shining Hearts",
    "details": "Sony PlayStation Portable exclusive",
    "id": "pspex214",
    "igdbId": 66402,
    "gbId": 32553,
    "gbGuid": "3030-32553",
    "tgdbId": null
  },
  {
    "name": "Shinobido: Tales of the Ninja",
    "details": "Sony PlayStation Portable exclusive",
    "id": "pspex215",
    "igdbId": 23108,
    "gbId": 24155,
    "gbGuid": "3030-24155",
    "tgdbId": null
  },
  {
    "name": "Smart Bomb",
    "details": "Sony PlayStation Portable exclusive",
    "id": "pspex216",
    "igdbId": 72930,
    "gbId": 22278,
    "gbGuid": "3030-22278",
    "tgdbId": 47784
  },
  {
    "name": "SOCOM: U.S. Navy SEALs Fireteam Bravo",
    "details": "Sony PlayStation Portable exclusive",
    "id": "pspex217",
    "igdbId": 24148,
    "gbId": 2972,
    "gbGuid": "3030-2972",
    "tgdbId": 10934
  },
  {
    "name": "SOCOM: U.S. Navy SEALs Fireteam Bravo 2",
    "details": "Sony PlayStation Portable exclusive",
    "id": "pspex218",
    "igdbId": 19431,
    "gbId": 5910,
    "gbGuid": "3030-5910",
    "tgdbId": 17246
  },
  {
    "name": "SOCOM: U.S. Navy SEALs Fireteam Bravo 3",
    "details": "Sony PlayStation Portable exclusive",
    "id": "pspex219",
    "igdbId": 21665,
    "gbId": 25894,
    "gbGuid": "3030-25894",
    "tgdbId": 19403
  },
  {
    "name": "SOCOM: U.S. Navy SEALs Tactical Strike",
    "details": "Sony PlayStation Portable exclusive",
    "id": "pspex220",
    "igdbId": 22530,
    "gbId": 7023,
    "gbGuid": "3030-7023",
    "tgdbId": 18933
  },
  {
    "name": "Sol Trigger",
    "details": "Sony PlayStation Portable exclusive",
    "id": "pspex221",
    "igdbId": 38467,
    "gbId": 39585,
    "gbGuid": "3030-39585",
    "tgdbId": 31489
  },
  {
    "name": "Sonic Rivals",
    "details": "Sony PlayStation Portable exclusive",
    "id": "pspex222",
    "igdbId": 19260,
    "gbId": 836,
    "gbGuid": "3030-836",
    "tgdbId": 18037
  },
  {
    "name": "Sonic Rivals 2",
    "details": "Sony PlayStation Portable exclusive",
    "id": "pspex223",
    "igdbId": 19262,
    "gbId": 20583,
    "gbGuid": "3030-20583",
    "tgdbId": 18038
  },
  {
    "name": "SoulCalibur: Broken Destiny",
    "details": "Sony PlayStation Portable exclusive",
    "id": "pspex224",
    "igdbId": 1568,
    "gbId": 26088,
    "gbGuid": "3030-26088",
    "tgdbId": 7116
  },
  {
    "name": "Sound of the Sky",
    "details": "Sony PlayStation Portable exclusive",
    "id": "pspex225",
    "igdbId": null,
    "gbId": null,
    "gbGuid": null,
    "tgdbId": null
  },
  {
    "name": "Tom Clancy's Splinter Cell Essentials",
    "details": "Sony PlayStation Portable exclusive",
    "id": "pspex226",
    "igdbId": 22632,
    "gbId": 13667,
    "gbGuid": "3030-13667",
    "tgdbId": 19412
  },
  {
    "name": "Star Wars Battlefront: Renegade Squadron",
    "details": "Sony PlayStation Portable exclusive",
    "id": "pspex227",
    "igdbId": 23063,
    "gbId": 20614,
    "gbGuid": "3030-20614",
    "tgdbId": 7072
  },
  {
    "name": "Steambot Chronicles: Battle Tournament",
    "details": "Sony PlayStation Portable exclusive",
    "id": "pspex228",
    "igdbId": 42891,
    "gbId": 25806,
    "gbGuid": "3030-25806",
    "tgdbId": 15048
  },
  {
    "name": "Street Riders",
    "details": "Sony PlayStation Portable exclusive",
    "id": "pspex229",
    "igdbId": 46017,
    "gbId": 12962,
    "gbGuid": "3030-12962",
    "tgdbId": 18722
  },
  {
    "name": "Summon Night 5",
    "details": "Sony PlayStation Portable exclusive",
    "id": "pspex230",
    "igdbId": 13110,
    "gbId": 39159,
    "gbGuid": "3030-39159",
    "tgdbId": 36914
  },
  {
    "name": "Sunday VS Magazine Shuuketsu! Choujou Daikessen",
    "details": "Sony PlayStation Portable exclusive",
    "id": "pspex231",
    "igdbId": 42841,
    "gbId": null,
    "gbGuid": null,
    "tgdbId": 19460
  },
  {
    "name": "SWAT: Target Liberty",
    "details": "Sony PlayStation Portable exclusive",
    "id": "pspex232",
    "igdbId": 319,
    "gbId": 22538,
    "gbGuid": "3030-22538",
    "tgdbId": 19409
  },
  {
    "name": "Sweet Fuse: At Your Side",
    "details": "Sony PlayStation Portable exclusive",
    "id": "pspex233",
    "igdbId": 20103,
    "gbId": 41592,
    "gbGuid": "3030-41592",
    "tgdbId": 17915
  },
  {
    "name": "Taishō Baseball Girls",
    "details": "Sony PlayStation Portable exclusive",
    "id": "pspex234",
    "igdbId": null,
    "gbId": null,
    "gbGuid": null,
    "tgdbId": null
  },
  {
    "name": "Taito Legends Power-Up",
    "details": "Sony PlayStation Portable exclusive",
    "id": "pspex235",
    "igdbId": 23098,
    "gbId": 18339,
    "gbGuid": "3030-18339",
    "tgdbId": 31178
  },
  {
    "name": "Tales of Phantasia: Narikiri Dungeon X",
    "details": "Sony PlayStation Portable exclusive",
    "id": "pspex236",
    "igdbId": 42864,
    "gbId": 30419,
    "gbGuid": "3030-30419",
    "tgdbId": 19015
  },
  {
    "name": "Tales of the Heroes: Twin Brave",
    "details": "Sony PlayStation Portable exclusive",
    "id": "pspex237",
    "igdbId": 42760,
    "gbId": 43498,
    "gbGuid": "3030-43498",
    "tgdbId": 24345
  },
  {
    "name": "Tales of the World: Radiant Mythology",
    "details": "Sony PlayStation Portable exclusive",
    "id": "pspex238",
    "igdbId": 19159,
    "gbId": 21990,
    "gbGuid": "3030-21990",
    "tgdbId": 13967
  },
  {
    "name": "Tales of the World: Radiant Mythology 2",
    "details": "Sony PlayStation Portable exclusive",
    "id": "pspex239",
    "igdbId": 42794,
    "gbId": 23947,
    "gbGuid": "3030-23947",
    "tgdbId": 25940
  },
  {
    "name": "Tales of the World: Radiant Mythology 3",
    "details": "Sony PlayStation Portable exclusive",
    "id": "pspex240",
    "igdbId": 42793,
    "gbId": 36342,
    "gbGuid": "3030-36342",
    "tgdbId": 25941
  },
  {
    "name": "Tales of VS.",
    "details": "Sony PlayStation Portable exclusive",
    "id": "pspex241",
    "igdbId": 42723,
    "gbId": 25770,
    "gbGuid": "3030-25770",
    "tgdbId": 43801
  },
  {
    "name": "Tantei Opera: Milky Holmes",
    "details": "Sony PlayStation Portable exclusive",
    "id": "pspex242",
    "igdbId": 38481,
    "gbId": null,
    "gbGuid": null,
    "tgdbId": 26908
  },
  {
    "name": "Tenchu: Time Of The Assassins",
    "details": "Sony PlayStation Portable exclusive",
    "id": "pspex243",
    "igdbId": 44512,
    "gbId": 21002,
    "gbGuid": "3030-21002",
    "tgdbId": 19523
  },
  {
    "name": "Terror of the Stratus",
    "details": "Sony PlayStation Portable exclusive",
    "id": "pspex244",
    "igdbId": null,
    "gbId": null,
    "gbGuid": null,
    "tgdbId": null
  },
  {
    "name": "Tiger & Bunny: Hero's Day",
    "details": "Sony PlayStation Portable exclusive",
    "id": "pspex245",
    "igdbId": 63842,
    "gbId": 41548,
    "gbGuid": "3030-41548",
    "tgdbId": null
  },
  {
    "name": "Tokimeki Memorial 4",
    "details": "Sony PlayStation Portable exclusive",
    "id": "pspex246",
    "igdbId": 67379,
    "gbId": 28973,
    "gbGuid": "3030-28973",
    "tgdbId": null
  },
  {
    "name": "Tokyo Mono Hara Shi: Karasu no Mori Gakuen Kitan",
    "details": "Sony PlayStation Portable exclusive",
    "id": "pspex247",
    "igdbId": 67287,
    "gbId": 29334,
    "gbGuid": "3030-29334",
    "tgdbId": null
  },
  {
    "name": "Tony Hawk's Underground 2 Remix",
    "details": "Sony PlayStation Portable exclusive",
    "id": "pspex248",
    "igdbId": 22311,
    "gbId": 18231,
    "gbGuid": "3030-18231",
    "tgdbId": 20096
  },
  {
    "name": "Toradora! Portable",
    "details": "Sony PlayStation Portable exclusive",
    "id": "pspex249",
    "igdbId": 42752,
    "gbId": 46604,
    "gbGuid": "3030-46604",
    "tgdbId": 32170
  },
  {
    "name": "Traxxpad: Portable Studio",
    "details": "Sony PlayStation Portable exclusive",
    "id": "pspex250",
    "igdbId": 71039,
    "gbId": 915,
    "gbGuid": "3030-915",
    "tgdbId": null
  },
  {
    "name": "Tsukumonogatari",
    "details": "Sony PlayStation Portable exclusive",
    "id": "pspex251",
    "igdbId": null,
    "gbId": null,
    "gbGuid": null,
    "tgdbId": null
  },
  {
    "name": "Ultimate Ghosts 'n Goblins",
    "details": "Sony PlayStation Portable exclusive",
    "id": "pspex252",
    "igdbId": 12481,
    "gbId": null,
    "gbGuid": null,
    "tgdbId": 69
  },
  {
    "name": "Ultraman Fighting Evolution 0",
    "details": "Sony PlayStation Portable exclusive",
    "id": "pspex253",
    "igdbId": 64212,
    "gbId": 40743,
    "gbGuid": "3030-40743",
    "tgdbId": null
  },
  {
    "name": "Undead Knights",
    "details": "Sony PlayStation Portable exclusive",
    "id": "pspex254",
    "igdbId": 23358,
    "gbId": 26889,
    "gbGuid": "3030-26889",
    "tgdbId": 14620
  },
  {
    "name": "Untold Legends: Brotherhood of the Blade",
    "details": "Sony PlayStation Portable exclusive",
    "id": "pspex255",
    "igdbId": 22508,
    "gbId": 3247,
    "gbGuid": "3030-3247",
    "tgdbId": 7121
  },
  {
    "name": "Untold Legends: The Warrior's Code",
    "details": "Sony PlayStation Portable exclusive",
    "id": "pspex256",
    "igdbId": 23006,
    "gbId": 2603,
    "gbGuid": "3030-2603",
    "tgdbId": 13394
  },
  {
    "name": "Valhalla Knights",
    "details": "Sony PlayStation Portable exclusive",
    "id": "pspex257",
    "igdbId": 20073,
    "gbId": 16776,
    "gbGuid": "3030-16776",
    "tgdbId": 13048
  },
  {
    "name": "Valhalla Knights 2",
    "details": "Sony PlayStation Portable exclusive",
    "id": "pspex258",
    "igdbId": 20071,
    "gbId": 21162,
    "gbGuid": "3030-21162",
    "tgdbId": 7122
  },
  {
    "name": "Valkyria Chronicles III",
    "details": "Sony PlayStation Portable exclusive",
    "id": "pspex259",
    "igdbId": 14675,
    "gbId": null,
    "gbGuid": null,
    "tgdbId": 27474
  },
  {
    "name": "Virtua Tennis 4: World Tour Edition",
    "details": "Sony PlayStation Portable exclusive",
    "id": "pspex260",
    "igdbId": 22312,
    "gbId": 9908,
    "gbGuid": "3030-9908",
    "tgdbId": 13315
  },
  {
    "name": "Warhammer: Battle for Atluma",
    "details": "Sony PlayStation Portable exclusive",
    "id": "pspex261",
    "igdbId": 28882,
    "gbId": 7518,
    "gbGuid": "3030-7518",
    "tgdbId": 40038
  },
  {
    "name": "What Did I Do to Deserve This, My Lord!?",
    "details": "Sony PlayStation Portable exclusive",
    "id": "pspex262",
    "igdbId": 21577,
    "gbId": 24119,
    "gbGuid": "3030-24119",
    "tgdbId": 22133
  },
  {
    "name": "What Did I Do to Deserve This, My Lord!? 2",
    "details": "Sony PlayStation Portable exclusive",
    "id": "pspex263",
    "igdbId": 22968,
    "gbId": 24120,
    "gbGuid": "3030-24120",
    "tgdbId": 24347
  },
  {
    "name": "White Knight Chronicles: Origins",
    "details": "Sony PlayStation Portable exclusive",
    "id": "pspex264",
    "igdbId": 42811,
    "gbId": 33334,
    "gbGuid": "3030-33334",
    "tgdbId": 21431
  },
  {
    "name": "Wild Arms XF",
    "details": "Sony PlayStation Portable exclusive",
    "id": "pspex265",
    "igdbId": 1683,
    "gbId": 21961,
    "gbGuid": "3030-21961",
    "tgdbId": 14091
  },
  {
    "name": "Wipeout Pure",
    "details": "Sony PlayStation Portable exclusive",
    "id": "pspex266",
    "igdbId": 1542,
    "gbId": 14796,
    "gbGuid": "3030-14796",
    "tgdbId": 7123
  },
  {
    "name": "WTF: Work Time Fun",
    "details": "Sony PlayStation Portable exclusive",
    "id": "pspex267",
    "igdbId": 42853,
    "gbId": 15646,
    "gbGuid": "3030-15646",
    "tgdbId": 15060
  },
  {
    "name": "WRC: FIA World Rally Championship",
    "details": "Sony PlayStation Portable exclusive",
    "id": "pspex268",
    "igdbId": 119183,
    "gbId": 31982,
    "gbGuid": "3030-31982",
    "tgdbId": 5278
  },
  {
    "name": "World Tour Soccer",
    "details": "Sony PlayStation Portable exclusive",
    "id": "pspex269",
    "igdbId": 22291,
    "gbId": 28436,
    "gbGuid": "3030-28436",
    "tgdbId": 7124
  },
  {
    "name": "Young Thor",
    "details": "Sony PlayStation Portable exclusive",
    "id": "pspex270",
    "igdbId": 20467,
    "gbId": 32318,
    "gbGuid": "3030-32318",
    "tgdbId": 26425
  },
  {
    "name": "Ys vs. Sora no Kiseki: Alternative Saga",
    "details": "Sony PlayStation Portable exclusive",
    "id": "pspex271",
    "igdbId": 42772,
    "gbId": 30364,
    "gbGuid": "3030-30364",
    "tgdbId": 24887
  },
  {
    "name": "Z.H.P. Unlosing Ranger vs Darkdeath Evilman",
    "details": "Sony PlayStation Portable exclusive",
    "id": "pspex272",
    "igdbId": 19816,
    "gbId": null,
    "gbGuid": null,
    "tgdbId": 15051
  },
  {
    "name": "Zettai Zetsumei Toshi 3",
    "details": "Sony PlayStation Portable exclusive",
    "id": "pspex273",
    "igdbId": 11697,
    "gbId": 25230,
    "gbGuid": "3030-25230",
    "tgdbId": 61696
  },
  {
    "name": "Zombie Tycoon",
    "details": "Sony PlayStation Portable exclusive",
    "id": "pspex274",
    "igdbId": 9295,
    "gbId": 30138,
    "gbGuid": "3030-30138",
    "tgdbId": 26431
  }
]