[
  {
    "name": "MLB Redsox Face plate",
    "id": "xb360ae1",
    "details": "part of Yankee's logo in the middle of Redsox logo",
    "image": "https://iamerror.gamehacking.org/Microsoft/Xbox360/redsoxfacepl.JPG",
    "type": "Printing",
    "igdbId": null,
    "gbId": null,
    "gbGuid": null
  },
  {
    "name": "Titanfall Controller",
    "id": "xb360ae2",
    "details": "PEGI rating should be 16 not 18",
    "image": "https://iamerror.gamehacking.org/Microsoft/Xbox360/titanfallcontroller.jpg",
    "type": "Printing",
    "igdbId": null,
    "gbId": null,
    "gbGuid": null
  }
]
